{
 "USDC@Ethereum": {
  "usd": 0.999813,
  "source": "CoinGecko",
  "ts": "2026-07-03T19:08:41Z"
 },
 "USDC_ARB@Arbitrum": {
  "usd": 0.999813,
  "source": "CoinGecko",
  "ts": "2026-07-03T19:08:41Z"
 },
 "USDC_SOL@Solana": {
  "usd": 0.999813,
  "source": "CoinGecko",
  "ts": "2026-07-03T19:08:41Z"
 },
 "USDC_OP@Optimism": {
  "usd": 0.999813,
  "source": "CoinGecko",
  "ts": "2026-07-03T19:08:41Z"
 },
 "USDC_POL@Polygon": {
  "usd": 0.999813,
  "source": "CoinGecko",
  "ts": "2026-07-03T19:08:41Z"
 },
 "USDC_BSC@BSC": {
  "usd": 0.999813,
  "source": "CoinGecko",
  "ts": "2026-07-03T19:08:41Z"
 },
 "USDC_AVAX@Avalanche": {
  "usd": 0.999813,
  "source": "CoinGecko",
  "ts": "2026-07-03T19:08:41Z"
 },
 "USDC_BASE@Base": {
  "usd": 0.999813,
  "source": "CoinGecko",
  "ts": "2026-07-03T19:08:41Z"
 },
 "USDC_ETH@Ethereum": {
  "usd": 0.999813,
  "source": "CoinGecko",
  "ts": "2026-07-03T19:08:41Z"
 },
 "ETH@Ethereum": {
  "usd": 1736.95,
  "source": "CoinGecko",
  "ts": "2026-07-03T19:08:41Z"
 },
 "BTC@Bitcoin": {
  "usd": 62113.0,
  "source": "CoinGecko",
  "ts": "2026-07-03T19:08:41Z"
 },
 "DOGE@Dogecoin": {
  "usd": 0.076749,
  "source": "CoinGecko",
  "ts": "2026-07-03T19:08:41Z"
 },
 "DOGE2@Solana": {
  "usd": 0.076749,
  "source": "CoinGecko",
  "ts": "2026-07-03T19:08:41Z"
 },
 "SOL@Solana": {
  "usd": 82.09,
  "source": "CoinGecko",
  "ts": "2026-07-03T19:08:41Z"
 },
 "USDT@Ethereum": {
  "usd": 0.999058,
  "source": "CoinGecko",
  "ts": "2026-07-03T19:08:41Z"
 },
 "USDT_ARB@Arbitrum": {
  "usd": 0.999058,
  "source": "CoinGecko",
  "ts": "2026-07-03T19:08:41Z"
 },
 "USDT_POL@Polygon": {
  "usd": 0.999058,
  "source": "CoinGecko",
  "ts": "2026-07-03T19:08:41Z"
 },
 "USDT_BSC@BSC": {
  "usd": 0.999058,
  "source": "CoinGecko",
  "ts": "2026-07-03T19:08:41Z"
 },
 "USDT_OP@Optimism": {
  "usd": 0.999058,
  "source": "CoinGecko",
  "ts": "2026-07-03T19:08:41Z"
 },
 "USDT_AVAX@Avalanche": {
  "usd": 0.999058,
  "source": "CoinGecko",
  "ts": "2026-07-03T19:08:41Z"
 },
 "USDT_ETH@Ethereum": {
  "usd": 0.999058,
  "source": "CoinGecko",
  "ts": "2026-07-03T19:08:41Z"
 },
 "WBTC@Ethereum": {
  "usd": 62132.0,
  "source": "CoinGecko",
  "ts": "2026-07-03T19:08:41Z"
 },
 "WBTC_ARB@Arbitrum": {
  "usd": 62132.0,
  "source": "CoinGecko",
  "ts": "2026-07-03T19:08:41Z"
 },
 "WBTC_OP@Optimism": {
  "usd": 62132.0,
  "source": "CoinGecko",
  "ts": "2026-07-03T19:08:41Z"
 },
 "WBTC_POL@Polygon": {
  "usd": 62132.0,
  "source": "CoinGecko",
  "ts": "2026-07-03T19:08:41Z"
 },
 "WBTC_ETH@Ethereum": {
  "usd": 62132.0,
  "source": "CoinGecko",
  "ts": "2026-07-03T19:08:41Z"
 },
 "LINK@Ethereum": {
  "usd": 7.9,
  "source": "CoinGecko",
  "ts": "2026-07-03T19:08:41Z"
 },
 "LINK_ARB@Arbitrum": {
  "usd": 7.9,
  "source": "CoinGecko",
  "ts": "2026-07-03T19:08:41Z"
 },
 "LINK_POL@Polygon": {
  "usd": 7.9,
  "source": "CoinGecko",
  "ts": "2026-07-03T19:08:41Z"
 },
 "LINK_BSC@BSC": {
  "usd": 7.9,
  "source": "CoinGecko",
  "ts": "2026-07-03T19:08:41Z"
 },
 "LINK_AVAX@Avalanche": {
  "usd": 7.9,
  "source": "CoinGecko",
  "ts": "2026-07-03T19:08:41Z"
 },
 "LINK_OP@Optimism": {
  "usd": 7.9,
  "source": "CoinGecko",
  "ts": "2026-07-03T19:08:41Z"
 },
 "LINK_ETH@Ethereum": {
  "usd": 7.9,
  "source": "CoinGecko",
  "ts": "2026-07-03T19:08:41Z"
 },
 "stETH@Ethereum": {
  "usd": 1736.71,
  "source": "CoinGecko",
  "ts": "2026-07-03T19:08:41Z"
 },
 "STETH_ETH@Ethereum": {
  "usd": 1736.71,
  "source": "CoinGecko",
  "ts": "2026-07-03T19:08:41Z"
 },
 "DAI@Ethereum": {
  "usd": 0.999683,
  "source": "CoinGecko",
  "ts": "2026-07-03T19:08:41Z"
 },
 "DAI_ARB@Arbitrum": {
  "usd": 0.999683,
  "source": "CoinGecko",
  "ts": "2026-07-03T19:08:41Z"
 },
 "DAI_OP@Optimism": {
  "usd": 0.999683,
  "source": "CoinGecko",
  "ts": "2026-07-03T19:08:41Z"
 },
 "DAI_POL@Polygon": {
  "usd": 0.999683,
  "source": "CoinGecko",
  "ts": "2026-07-03T19:08:41Z"
 },
 "DAI_BSC@BSC": {
  "usd": 0.999683,
  "source": "CoinGecko",
  "ts": "2026-07-03T19:08:41Z"
 },
 "DAI_AVAX@Avalanche": {
  "usd": 0.999683,
  "source": "CoinGecko",
  "ts": "2026-07-03T19:08:41Z"
 },
 "XRP@XRPL": {
  "usd": 1.13,
  "source": "CoinGecko",
  "ts": "2026-07-03T19:08:41Z"
 },
 "UNI@Ethereum": {
  "usd": 3.24,
  "source": "CoinGecko",
  "ts": "2026-07-03T19:08:41Z"
 },
 "UNI_ARB@Arbitrum": {
  "usd": 3.24,
  "source": "CoinGecko",
  "ts": "2026-07-03T19:08:41Z"
 },
 "UNI_OP@Optimism": {
  "usd": 3.24,
  "source": "CoinGecko",
  "ts": "2026-07-03T19:08:41Z"
 },
 "UNI_POL@Polygon": {
  "usd": 3.24,
  "source": "CoinGecko",
  "ts": "2026-07-03T19:08:41Z"
 },
 "UNI_ETH@Ethereum": {
  "usd": 3.24,
  "source": "CoinGecko",
  "ts": "2026-07-03T19:08:41Z"
 },
 "AAVE@Ethereum": {
  "usd": 87.36,
  "source": "CoinGecko",
  "ts": "2026-07-03T19:08:41Z"
 },
 "AAVE_ARB@Arbitrum": {
  "usd": 87.36,
  "source": "CoinGecko",
  "ts": "2026-07-03T19:08:41Z"
 },
 "AAVE_OP@Optimism": {
  "usd": 87.36,
  "source": "CoinGecko",
  "ts": "2026-07-03T19:08:41Z"
 },
 "AAVE_POL@Polygon": {
  "usd": 87.36,
  "source": "CoinGecko",
  "ts": "2026-07-03T19:08:41Z"
 },
 "AAVE_AVAX@Avalanche": {
  "usd": 87.36,
  "source": "CoinGecko",
  "ts": "2026-07-03T19:08:41Z"
 },
 "LDO@Ethereum": {
  "usd": 0.267793,
  "source": "CoinGecko",
  "ts": "2026-07-03T19:08:41Z"
 },
 "LDO_ETH@Ethereum": {
  "usd": 0.267793,
  "source": "CoinGecko",
  "ts": "2026-07-03T19:08:41Z"
 },
 "SHIB@Ethereum": {
  "usd": 4.38e-06,
  "source": "CoinGecko",
  "ts": "2026-07-03T19:08:41Z"
 },
 "SHIB2@BSC": {
  "usd": 4.38e-06,
  "source": "CoinGecko",
  "ts": "2026-07-03T19:08:41Z"
 },
 "SHIB_ETH@Ethereum": {
  "usd": 4.38e-06,
  "source": "CoinGecko",
  "ts": "2026-07-03T19:08:41Z"
 },
 "BNB@BSC": {
  "usd": 567.58,
  "source": "CoinGecko",
  "ts": "2026-07-03T19:08:41Z"
 },
 "LTC@Litecoin": {
  "usd": 44.08,
  "source": "CoinGecko",
  "ts": "2026-07-03T19:08:41Z"
 },
 "PEPE@Ethereum": {
  "usd": 2.57e-06,
  "source": "CoinGecko",
  "ts": "2026-07-03T19:08:41Z"
 },
 "ARB@Arbitrum": {
  "usd": 0.079823,
  "source": "CoinGecko",
  "ts": "2026-07-03T19:08:41Z"
 },
 "ARB_TOKEN@Arbitrum": {
  "usd": 0.079823,
  "source": "CoinGecko",
  "ts": "2026-07-03T19:08:41Z"
 },
 "ARB_ETH@Ethereum": {
  "usd": 0.079823,
  "source": "CoinGecko",
  "ts": "2026-07-03T19:08:41Z"
 },
 "AVAX@Avalanche": {
  "usd": 6.87,
  "source": "CoinGecko",
  "ts": "2026-07-03T19:08:41Z"
 },
 "AVAX_MEME@Avalanche": {
  "usd": 6.87,
  "source": "CoinGecko",
  "ts": "2026-07-03T19:08:41Z"
 },
 "AVAX_NATIVE@Avalanche": {
  "usd": 6.87,
  "source": "CoinGecko",
  "ts": "2026-07-03T19:08:41Z"
 },
 "wstETH@Ethereum": {
  "usd": 2153.24,
  "source": "CoinGecko",
  "ts": "2026-07-03T19:08:41Z"
 },
 "CBETH@Base": {
  "usd": 1971.45,
  "source": "CoinGecko",
  "ts": "2026-07-03T19:08:41Z"
 },
 "CBETH_BASE@Base": {
  "usd": 1971.45,
  "source": "CoinGecko",
  "ts": "2026-07-03T19:08:41Z"
 },
 "OP@Optimism": {
  "usd": 0.106531,
  "source": "CoinGecko",
  "ts": "2026-07-03T19:08:41Z"
 },
 "OP_TOKEN@Optimism": {
  "usd": 0.106531,
  "source": "CoinGecko",
  "ts": "2026-07-03T19:08:41Z"
 },
 "OP_ETH@Ethereum": {
  "usd": 0.106531,
  "source": "CoinGecko",
  "ts": "2026-07-03T19:08:41Z"
 },
 "SKY@Ethereum": {
  "usd": 0.058337,
  "source": "CoinGecko",
  "ts": "2026-07-03T19:08:41Z"
 },
 "CBBTC@Base": {
  "usd": 62097.0,
  "source": "CoinGecko",
  "ts": "2026-07-03T19:08:41Z"
 },
 "cbBTC@Base": {
  "usd": 62097.0,
  "source": "CoinGecko",
  "ts": "2026-07-03T19:08:41Z"
 },
 "CBBTC_ETH@Ethereum": {
  "usd": 62097.0,
  "source": "CoinGecko",
  "ts": "2026-07-03T19:08:41Z"
 },
 "USDS@Ethereum": {
  "usd": 0.999703,
  "source": "CoinGecko",
  "ts": "2026-07-03T19:08:41Z"
 },
 "BONK@Solana": {
  "usd": 4.54e-06,
  "source": "CoinGecko",
  "ts": "2026-07-03T19:08:41Z"
 },
 "PENGU@Solana": {
  "usd": 0.0067459,
  "source": "CoinGecko",
  "ts": "2026-07-03T19:08:41Z"
 },
 "MKR@Ethereum": {
  "usd": 1356.3,
  "source": "CoinGecko",
  "ts": "2026-07-03T19:08:41Z"
 },
 "MKR_ETH@Ethereum": {
  "usd": 1356.3,
  "source": "CoinGecko",
  "ts": "2026-07-03T19:08:41Z"
 },
 "WIF@Solana": {
  "usd": 0.176628,
  "source": "CoinGecko",
  "ts": "2026-07-03T19:08:41Z"
 },
 "AERO@Base": {
  "usd": 0.549709,
  "source": "CoinGecko",
  "ts": "2026-07-03T19:08:41Z"
 },
 "GRT@Ethereum": {
  "usd": 0.01870488,
  "source": "CoinGecko",
  "ts": "2026-07-03T19:08:41Z"
 },
 "GRT_ARB@Arbitrum": {
  "usd": 0.01870488,
  "source": "CoinGecko",
  "ts": "2026-07-03T19:08:41Z"
 },
 "GRT_ETH@Ethereum": {
  "usd": 0.01870488,
  "source": "CoinGecko",
  "ts": "2026-07-03T19:08:41Z"
 },
 "ENS@Ethereum": {
  "usd": 4.36,
  "source": "CoinGecko",
  "ts": "2026-07-03T19:08:41Z"
 },
 "PAXG@Ethereum": {
  "usd": 4165.34,
  "source": "CoinGecko",
  "ts": "2026-07-03T19:08:41Z"
 },
 "IMX@Ethereum": {
  "usd": 0.12987,
  "source": "CoinGecko",
  "ts": "2026-07-03T19:08:41Z"
 },
 "IMX_ETH@Ethereum": {
  "usd": 0.12987,
  "source": "CoinGecko",
  "ts": "2026-07-03T19:08:41Z"
 },
 "PENDLE@Ethereum": {
  "usd": 1.49,
  "source": "CoinGecko",
  "ts": "2026-07-03T19:08:41Z"
 },
 "PENDLE_ARB@Arbitrum": {
  "usd": 1.49,
  "source": "CoinGecko",
  "ts": "2026-07-03T19:08:41Z"
 },
 "PENDLE_B@Base": {
  "usd": 1.49,
  "source": "CoinGecko",
  "ts": "2026-07-03T19:08:41Z"
 },
 "EIGEN@Ethereum": {
  "usd": 0.211263,
  "source": "CoinGecko",
  "ts": "2026-07-03T19:08:41Z"
 },
 "GMX@Arbitrum": {
  "usd": 6.01,
  "source": "CoinGecko",
  "ts": "2026-07-03T19:08:41Z"
 },
 "RNDR@Ethereum": {
  "usd": 1.6,
  "source": "CoinGecko",
  "ts": "2026-07-03T19:08:41Z"
 },
 "RNDR@Solana": {
  "usd": 1.6,
  "source": "CoinGecko",
  "ts": "2026-07-03T19:08:41Z"
 },
 "RNDR_SOL@Solana": {
  "usd": 1.6,
  "source": "CoinGecko",
  "ts": "2026-07-03T19:08:41Z"
 },
 "RENDER@Ethereum": {
  "usd": 1.6,
  "source": "CoinGecko",
  "ts": "2026-07-03T19:08:41Z"
 },
 "BCH@Bitcoin": {
  "usd": 227.52,
  "source": "CoinGecko",
  "ts": "2026-07-03T19:08:41Z"
 },
 "SNX@Ethereum": {
  "usd": 0.233858,
  "source": "CoinGecko",
  "ts": "2026-07-03T19:08:41Z"
 },
 "SNS@Optimism": {
  "usd": 0.233858,
  "source": "CoinGecko",
  "ts": "2026-07-03T19:08:41Z"
 },
 "SNX_ARB@Arbitrum": {
  "usd": 0.233858,
  "source": "CoinGecko",
  "ts": "2026-07-03T19:08:41Z"
 },
 "SNS_OP@Optimism": {
  "usd": 0.233858,
  "source": "CoinGecko",
  "ts": "2026-07-03T19:08:41Z"
 },
 "SNX_ETH@Ethereum": {
  "usd": 0.233858,
  "source": "CoinGecko",
  "ts": "2026-07-03T19:08:41Z"
 },
 "CRV@Ethereum": {
  "usd": 0.207062,
  "source": "CoinGecko",
  "ts": "2026-07-03T19:08:41Z"
 },
 "CRV_ARB@Arbitrum": {
  "usd": 0.207062,
  "source": "CoinGecko",
  "ts": "2026-07-03T19:08:41Z"
 },
 "CRV_ETH@Ethereum": {
  "usd": 0.207062,
  "source": "CoinGecko",
  "ts": "2026-07-03T19:08:41Z"
 },
 "1INCH@Ethereum": {
  "usd": 0.072004,
  "source": "CoinGecko",
  "ts": "2026-07-03T19:08:41Z"
 },
 "RPL@Ethereum": {
  "usd": 1.63,
  "source": "CoinGecko",
  "ts": "2026-07-03T19:08:41Z"
 },
 "RPL_ETH@Ethereum": {
  "usd": 1.63,
  "source": "CoinGecko",
  "ts": "2026-07-03T19:08:41Z"
 },
 "rETH@Ethereum": {
  "usd": 2026.71,
  "source": "CoinGecko",
  "ts": "2026-07-03T19:08:41Z"
 },
 "RETH_ETH@Ethereum": {
  "usd": 2026.71,
  "source": "CoinGecko",
  "ts": "2026-07-03T19:08:41Z"
 },
 "ENA@Ethereum": {
  "usd": 0.078872,
  "source": "CoinGecko",
  "ts": "2026-07-03T19:08:41Z"
 },
 "RON@Ethereum": {
  "usd": 0.061006,
  "source": "CoinGecko",
  "ts": "2026-07-03T19:08:41Z"
 },
 "CAKE@BSC": {
  "usd": 1.39,
  "source": "CoinGecko",
  "ts": "2026-07-03T19:08:41Z"
 },
 "CAKE_BSC@BSC": {
  "usd": 1.39,
  "source": "CoinGecko",
  "ts": "2026-07-03T19:08:41Z"
 },
 "CHZ@Ethereum": {
  "usd": 0.01850941,
  "source": "CoinGecko",
  "ts": "2026-07-03T19:08:41Z"
 },
 "CHZ_ETH@Ethereum": {
  "usd": 0.01850941,
  "source": "CoinGecko",
  "ts": "2026-07-03T19:08:41Z"
 },
 "FET@Ethereum": {
  "usd": 0.187314,
  "source": "CoinGecko",
  "ts": "2026-07-03T19:08:41Z"
 },
 "FET_ETH@Ethereum": {
  "usd": 0.187314,
  "source": "CoinGecko",
  "ts": "2026-07-03T19:08:41Z"
 },
 "USDe@Ethereum": {
  "usd": 0.998584,
  "source": "CoinGecko",
  "ts": "2026-07-03T19:08:41Z"
 },
 "ONDO@Ethereum": {
  "usd": 0.334764,
  "source": "CoinGecko",
  "ts": "2026-07-03T19:08:41Z"
 },
 "OKB@Ethereum": {
  "usd": 80.55,
  "source": "CoinGecko",
  "ts": "2026-07-03T19:08:41Z"
 },
 "GHO@Ethereum": {
  "usd": 0.998056,
  "source": "CoinGecko",
  "ts": "2026-07-03T19:08:41Z"
 },
 "COMP@Ethereum": {
  "usd": 16.8,
  "source": "CoinGecko",
  "ts": "2026-07-03T19:08:41Z"
 },
 "COMP_ETH@Ethereum": {
  "usd": 16.8,
  "source": "CoinGecko",
  "ts": "2026-07-03T19:08:41Z"
 },
 "FLOKI@Ethereum": {
  "usd": 2.307e-05,
  "source": "CoinGecko",
  "ts": "2026-07-03T19:08:41Z"
 },
 "FLOKI2@BSC": {
  "usd": 2.307e-05,
  "source": "CoinGecko",
  "ts": "2026-07-03T19:08:41Z"
 },
 "PYTH@Solana": {
  "usd": 0.0391687,
  "source": "CoinGecko",
  "ts": "2026-07-03T19:08:41Z"
 },
 "VIRTUAL@Base": {
  "usd": 0.568207,
  "source": "CoinGecko",
  "ts": "2026-07-03T19:08:41Z"
 },
 "VIRTUAL2@Solana": {
  "usd": 0.568207,
  "source": "CoinGecko",
  "ts": "2026-07-03T19:08:41Z"
 },
 "VIRTUAL_BASE@Base": {
  "usd": 0.568207,
  "source": "CoinGecko",
  "ts": "2026-07-03T19:08:41Z"
 },
 "BLUR@Ethereum": {
  "usd": 0.01537465,
  "source": "CoinGecko",
  "ts": "2026-07-03T19:08:41Z"
 },
 "BRETT@Base": {
  "usd": 0.00014372,
  "source": "CoinGecko",
  "ts": "2026-07-03T19:08:41Z"
 },
 "PSG@Ethereum": {
  "usd": 0.52553,
  "source": "CoinGecko",
  "ts": "2026-07-03T19:08:41Z"
 },
 "BAR@Ethereum": {
  "usd": 0.272276,
  "source": "CoinGecko",
  "ts": "2026-07-03T19:08:41Z"
 },
 "JTO@Solana": {
  "usd": 0.781444,
  "source": "CoinGecko",
  "ts": "2026-07-03T19:08:41Z"
 },
 "JUP@Solana": {
  "usd": 0.24472,
  "source": "CoinGecko",
  "ts": "2026-07-03T19:08:41Z"
 },
 "RAY@Solana": {
  "usd": 0.724805,
  "source": "CoinGecko",
  "ts": "2026-07-03T19:08:41Z"
 },
 "PYUSD@Ethereum": {
  "usd": 0.999951,
  "source": "CoinGecko",
  "ts": "2026-07-03T19:08:41Z"
 },
 "PYUSD_ETH@Ethereum": {
  "usd": 0.999951,
  "source": "CoinGecko",
  "ts": "2026-07-03T19:08:41Z"
 },
 "BAL@Ethereum": {
  "usd": 0.091366,
  "source": "CoinGecko",
  "ts": "2026-07-03T19:08:41Z"
 },
 "BAL_ETH@Ethereum": {
  "usd": 0.091366,
  "source": "CoinGecko",
  "ts": "2026-07-03T19:08:41Z"
 },
 "SPX@Ethereum": {
  "usd": 0.404257,
  "source": "CoinGecko",
  "ts": "2026-07-03T19:08:41Z"
 },
 "WLD@Ethereum": {
  "usd": 0.429133,
  "source": "CoinGecko",
  "ts": "2026-07-03T19:08:41Z"
 },
 "DEGEN@Base": {
  "usd": 0.00167694,
  "source": "CoinGecko",
  "ts": "2026-07-03T19:08:41Z"
 },
 "DGB@DigiByte": {
  "usd": 0.00245172,
  "source": "CoinGecko",
  "ts": "2026-07-03T19:08:41Z"
 },
 "BAT@Ethereum": {
  "usd": 0.083724,
  "source": "CoinGecko",
  "ts": "2026-07-03T19:08:41Z"
 },
 "BAT_ETH@Ethereum": {
  "usd": 0.083724,
  "source": "CoinGecko",
  "ts": "2026-07-03T19:08:41Z"
 },
 "LUSD@Ethereum": {
  "usd": 1.007,
  "source": "CoinGecko",
  "ts": "2026-07-03T19:08:41Z"
 },
 "POPCAT@Solana": {
  "usd": 0.051364,
  "source": "CoinGecko",
  "ts": "2026-07-03T19:08:41Z"
 },
 "FARTCOIN@Solana": {
  "usd": 0.166619,
  "source": "CoinGecko",
  "ts": "2026-07-03T19:08:41Z"
 },
 "MEW@Solana": {
  "usd": 0.00039147,
  "source": "CoinGecko",
  "ts": "2026-07-03T19:08:41Z"
 },
 "COW@Ethereum": {
  "usd": 0.149627,
  "source": "CoinGecko",
  "ts": "2026-07-03T19:08:41Z"
 },
 "MNT@Ethereum": {
  "usd": 0.439642,
  "source": "CoinGecko",
  "ts": "2026-07-03T19:08:41Z"
 },
 "STRK@Ethereum": {
  "usd": 0.03137791,
  "source": "CoinGecko",
  "ts": "2026-07-03T19:08:41Z"
 },
 "ZK@Ethereum": {
  "usd": 0.01077587,
  "source": "CoinGecko",
  "ts": "2026-07-03T19:08:41Z"
 },
 "CRO@Ethereum": {
  "usd": 0.061603,
  "source": "CoinGecko",
  "ts": "2026-07-03T19:08:41Z"
 },
 "VELO@Optimism": {
  "usd": 0.02348856,
  "source": "CoinGecko",
  "ts": "2026-07-03T19:08:41Z"
 },
 "YFI@Ethereum": {
  "usd": 1818.56,
  "source": "CoinGecko",
  "ts": "2026-07-03T19:08:41Z"
 },
 "YFI_ETH@Ethereum": {
  "usd": 1818.56,
  "source": "CoinGecko",
  "ts": "2026-07-03T19:08:41Z"
 },
 "FXS@Ethereum": {
  "usd": 0.2461,
  "source": "CoinGecko",
  "ts": "2026-07-03T19:08:41Z"
 },
 "FXS_ETH@Ethereum": {
  "usd": 0.2461,
  "source": "CoinGecko",
  "ts": "2026-07-03T19:08:41Z"
 },
 "FRAX@Ethereum": {
  "usd": 0.988555,
  "source": "CoinGecko",
  "ts": "2026-07-03T19:08:41Z"
 },
 "FRAX_BSC@BSC": {
  "usd": 0.988555,
  "source": "CoinGecko",
  "ts": "2026-07-03T19:08:41Z"
 },
 "CRVUSD@Ethereum": {
  "usd": 0.999201,
  "source": "CoinGecko",
  "ts": "2026-07-03T19:08:41Z"
 },
 "CVX@Ethereum": {
  "usd": 1.19,
  "source": "CoinGecko",
  "ts": "2026-07-03T19:08:41Z"
 },
 "CVX_ETH@Ethereum": {
  "usd": 1.19,
  "source": "CoinGecko",
  "ts": "2026-07-03T19:08:41Z"
 },
 "ai16Z@Solana": {
  "usd": 0.00044618,
  "source": "CoinGecko",
  "ts": "2026-07-03T19:08:41Z"
 },
 "MOG@Ethereum": {
  "usd": 1.16819e-07,
  "source": "CoinGecko",
  "ts": "2026-07-03T19:08:41Z"
 },
 "APE@Ethereum": {
  "usd": 0.14587,
  "source": "CoinGecko",
  "ts": "2026-07-03T19:08:41Z"
 },
 "BLAST@Ethereum": {
  "usd": 0.00027661,
  "source": "CoinGecko",
  "ts": "2026-07-03T19:08:41Z"
 },
 "JOE@Avalanche": {
  "usd": 0.02975356,
  "source": "CoinGecko",
  "ts": "2026-07-03T19:08:41Z"
 },
 "JOE_AVAX2@Avalanche": {
  "usd": 0.02975356,
  "source": "CoinGecko",
  "ts": "2026-07-03T19:08:41Z"
 },
 "MANA@Ethereum": {
  "usd": 0.072572,
  "source": "CoinGecko",
  "ts": "2026-07-03T19:08:41Z"
 },
 "MANA_ETH@Ethereum": {
  "usd": 0.072572,
  "source": "CoinGecko",
  "ts": "2026-07-03T19:08:41Z"
 },
 "SAND@Ethereum": {
  "usd": 0.051249,
  "source": "CoinGecko",
  "ts": "2026-07-03T19:08:41Z"
 },
 "SAND_ETH@Ethereum": {
  "usd": 0.051249,
  "source": "CoinGecko",
  "ts": "2026-07-03T19:08:41Z"
 },
 "AXS@Ethereum": {
  "usd": 1.051,
  "source": "CoinGecko",
  "ts": "2026-07-03T19:08:41Z"
 },
 "AXS_ETH@Ethereum": {
  "usd": 1.051,
  "source": "CoinGecko",
  "ts": "2026-07-03T19:08:41Z"
 },
 "OCEAN@Ethereum": {
  "usd": 0.114669,
  "source": "CoinGecko",
  "ts": "2026-07-03T19:08:41Z"
 },
 "OCEAN_ETH@Ethereum": {
  "usd": 0.114669,
  "source": "CoinGecko",
  "ts": "2026-07-03T19:08:41Z"
 },
 "ETHFI@Ethereum": {
  "usd": 0.36796,
  "source": "CoinGecko",
  "ts": "2026-07-03T19:08:41Z"
 },
 "sUSDe@Ethereum": {
  "usd": 1.24,
  "source": "CoinGecko",
  "ts": "2026-07-03T19:08:41Z"
 },
 "WEETH@Ethereum": {
  "usd": 1906.9,
  "source": "CoinGecko",
  "ts": "2026-07-03T19:08:41Z"
 },
 "eETH@Ethereum": {
  "usd": 1737.05,
  "source": "CoinGecko",
  "ts": "2026-07-03T19:08:41Z"
 },
 "MORPHO@Ethereum": {
  "usd": 1.95,
  "source": "CoinGecko",
  "ts": "2026-07-03T19:08:41Z"
 },
 "LQTY@Ethereum": {
  "usd": 0.189902,
  "source": "CoinGecko",
  "ts": "2026-07-03T19:08:41Z"
 },
 "DYDX@Ethereum": {
  "usd": 0.131588,
  "source": "CoinGecko",
  "ts": "2026-07-03T19:08:41Z"
 },
 "WOO@Arbitrum": {
  "usd": 0.01202474,
  "source": "CoinGecko",
  "ts": "2026-07-03T19:08:41Z"
 },
 "FRXETH@Ethereum": {
  "usd": 1736.36,
  "source": "CoinGecko",
  "ts": "2026-07-03T19:08:41Z"
 },
 "PNUT@Solana": {
  "usd": 0.04433594,
  "source": "CoinGecko",
  "ts": "2026-07-03T19:08:41Z"
 },
 "BOME@Solana": {
  "usd": 0.00043943,
  "source": "CoinGecko",
  "ts": "2026-07-03T19:08:41Z"
 },
 "TOSHI@Base": {
  "usd": 0.00011896,
  "source": "CoinGecko",
  "ts": "2026-07-03T19:08:41Z"
 },
 "PRIME@Ethereum": {
  "usd": 0.237234,
  "source": "CoinGecko",
  "ts": "2026-07-03T19:08:41Z"
 },
 "MAGIC@Arbitrum": {
  "usd": 0.04332737,
  "source": "CoinGecko",
  "ts": "2026-07-03T19:08:41Z"
 },
 "GMT@BSC": {
  "usd": 0.0079045,
  "source": "CoinGecko",
  "ts": "2026-07-03T19:08:41Z"
 },
 "GMT2@BSC": {
  "usd": 0.0079045,
  "source": "CoinGecko",
  "ts": "2026-07-03T19:08:41Z"
 },
 "sfrxETH@Ethereum": {
  "usd": 2018.48,
  "source": "CoinGecko",
  "ts": "2026-07-03T19:08:41Z"
 },
 "TRUMP@Solana": {
  "usd": 1.78,
  "source": "CoinGecko",
  "ts": "2026-07-03T19:08:41Z"
 },
 "TNSR@Solana": {
  "usd": 0.03508192,
  "source": "CoinGecko",
  "ts": "2026-07-03T19:08:41Z"
 },
 "TNSR2@Solana": {
  "usd": 0.03508192,
  "source": "CoinGecko",
  "ts": "2026-07-03T19:08:41Z"
 },
 "JUV@Ethereum": {
  "usd": 0.321211,
  "source": "CoinGecko",
  "ts": "2026-07-03T19:08:41Z"
 },
 "ACM@Ethereum": {
  "usd": 0.293589,
  "source": "CoinGecko",
  "ts": "2026-07-03T19:08:41Z"
 },
 "CITY@Ethereum": {
  "usd": 0.384709,
  "source": "CoinGecko",
  "ts": "2026-07-03T19:08:41Z"
 },
 "AGIX@Ethereum": {
  "usd": 0.083635,
  "source": "CoinGecko",
  "ts": "2026-07-03T19:08:41Z"
 },
 "AGIX_ETH@Ethereum": {
  "usd": 0.083635,
  "source": "CoinGecko",
  "ts": "2026-07-03T19:08:41Z"
 },
 "SUSHI@Ethereum": {
  "usd": 0.162038,
  "source": "CoinGecko",
  "ts": "2026-07-03T19:08:41Z"
 },
 "W@Ethereum": {
  "usd": 0.01004651,
  "source": "CoinGecko",
  "ts": "2026-07-03T19:08:41Z"
 },
 "AXL@Ethereum": {
  "usd": 0.04325386,
  "source": "CoinGecko",
  "ts": "2026-07-03T19:08:41Z"
 },
 "FLUID@Ethereum": {
  "usd": 0.954449,
  "source": "CoinGecko",
  "ts": "2026-07-03T19:08:41Z"
 },
 "INST@Ethereum": {
  "usd": 0.954449,
  "source": "CoinGecko",
  "ts": "2026-07-03T19:08:41Z"
 },
 "STG@Ethereum": {
  "usd": 0.156276,
  "source": "CoinGecko",
  "ts": "2026-07-03T19:08:41Z"
 },
 "BABYDOGE@BSC": {
  "usd": 3.04077e-10,
  "source": "CoinGecko",
  "ts": "2026-07-03T19:08:41Z"
 },
 "jitoSOL@Solana": {
  "usd": 105.66,
  "source": "CoinGecko",
  "ts": "2026-07-03T19:08:41Z"
 },
 "NEIRO@Ethereum": {
  "usd": 0.00620527,
  "source": "CoinGecko",
  "ts": "2026-07-03T19:08:41Z"
 },
 "TURBO@Ethereum": {
  "usd": 0.00089296,
  "source": "CoinGecko",
  "ts": "2026-07-03T19:08:41Z"
 },
 "ZEC@Zcash": {
  "usd": 460.46,
  "source": "CoinGecko",
  "ts": "2026-07-03T19:08:41Z"
 },
 "BANANA@Ethereum": {
  "usd": 3.18,
  "source": "CoinGecko",
  "ts": "2026-07-03T19:08:41Z"
 },
 "UNIBOT@Ethereum": {
  "usd": 0.611038,
  "source": "CoinGecko",
  "ts": "2026-07-03T19:08:41Z"
 },
 "KAITO@Ethereum": {
  "usd": 0.607933,
  "source": "CoinGecko",
  "ts": "2026-07-03T19:08:41Z"
 },
 "HNT@Solana": {
  "usd": 0.246505,
  "source": "CoinGecko",
  "ts": "2026-07-03T19:08:41Z"
 },
 "ORCA@Solana": {
  "usd": 1.25,
  "source": "CoinGecko",
  "ts": "2026-07-03T19:08:41Z"
 },
 "DRIFT@Solana": {
  "usd": 0.0161878,
  "source": "CoinGecko",
  "ts": "2026-07-03T19:08:41Z"
 },
 "GALA@Ethereum": {
  "usd": 0.0024837,
  "source": "CoinGecko",
  "ts": "2026-07-03T19:08:41Z"
 },
 "ARKM@Ethereum": {
  "usd": 0.120002,
  "source": "CoinGecko",
  "ts": "2026-07-03T19:08:41Z"
 },
 "FIL@Ethereum": {
  "usd": 0.798947,
  "source": "CoinGecko",
  "ts": "2026-07-03T19:08:41Z"
 },
 "KMNO@Solana": {
  "usd": 0.0195894,
  "source": "CoinGecko",
  "ts": "2026-07-03T19:08:41Z"
 },
 "mSOL@Solana": {
  "usd": 113.96,
  "source": "CoinGecko",
  "ts": "2026-07-03T19:08:41Z"
 },
 "SLP@Ethereum": {
  "usd": 0.00054861,
  "source": "CoinGecko",
  "ts": "2026-07-03T19:08:41Z"
 },
 "ELIZA@Solana": {
  "usd": 0.00014617,
  "source": "CoinGecko",
  "ts": "2026-07-03T19:08:41Z"
 },
 "PONKE@Solana": {
  "usd": 0.02444104,
  "source": "CoinGecko",
  "ts": "2026-07-03T19:08:41Z"
 },
 "PONKE@Base": {
  "usd": 0.02444104,
  "source": "CoinGecko",
  "ts": "2026-07-03T19:08:41Z"
 },
 "MOODENG@Solana": {
  "usd": 0.04361532,
  "source": "CoinGecko",
  "ts": "2026-07-03T19:08:41Z"
 },
 "BGB@Ethereum": {
  "usd": 1.71,
  "source": "CoinGecko",
  "ts": "2026-07-03T19:08:41Z"
 },
 "MUMU@Solana": {
  "usd": 5.1676e-08,
  "source": "CoinGecko",
  "ts": "2026-07-03T19:08:41Z"
 },
 "FDUSD@BSC": {
  "usd": 0.997018,
  "source": "CoinGecko",
  "ts": "2026-07-03T19:08:41Z"
 },
 "KCS@Ethereum": {
  "usd": 7.18,
  "source": "CoinGecko",
  "ts": "2026-07-03T19:08:41Z"
 },
 "GT@Ethereum": {
  "usd": 0.00015541,
  "source": "CoinGecko",
  "ts": "2026-07-03T19:08:41Z"
 },
 "USUAL@Ethereum": {
  "usd": 0.00941038,
  "source": "CoinGecko",
  "ts": "2026-07-03T19:08:41Z"
 },
 "EUROC@Ethereum": {
  "usd": 1.14,
  "source": "CoinGecko",
  "ts": "2026-07-03T19:08:41Z"
 },
 "EUROC_ETH@Ethereum": {
  "usd": 1.14,
  "source": "CoinGecko",
  "ts": "2026-07-03T19:08:41Z"
 },
 "PIPPIN@Solana": {
  "usd": 0.02118892,
  "source": "CoinGecko",
  "ts": "2026-07-03T19:08:41Z"
 },
 "LUNC@BSC": {
  "usd": 6.538e-05,
  "source": "CoinGecko",
  "ts": "2026-07-03T19:08:41Z"
 },
 "LUNC_BSC@BSC": {
  "usd": 6.538e-05,
  "source": "CoinGecko",
  "ts": "2026-07-03T19:08:41Z"
 },
 "HIGHER@Base": {
  "usd": 0.00017022,
  "source": "CoinGecko",
  "ts": "2026-07-03T19:08:41Z"
 },
 "GOAT@Solana": {
  "usd": 0.01453424,
  "source": "CoinGecko",
  "ts": "2026-07-03T19:08:41Z"
 },
 "CHILLGUY@Solana": {
  "usd": 0.00952931,
  "source": "CoinGecko",
  "ts": "2026-07-03T19:08:41Z"
 },
 "PEOPLE@Ethereum": {
  "usd": 0.00533992,
  "source": "CoinGecko",
  "ts": "2026-07-03T19:08:41Z"
 },
 "STEPN@Solana": {
  "usd": 0.00105237,
  "source": "CoinGecko",
  "ts": "2026-07-03T19:08:41Z"
 },
 "NMR@Ethereum": {
  "usd": 9.82,
  "source": "CoinGecko",
  "ts": "2026-07-03T19:08:41Z"
 },
 "NMR_ETH@Ethereum": {
  "usd": 9.82,
  "source": "CoinGecko",
  "ts": "2026-07-03T19:08:41Z"
 },
 "API3@Ethereum": {
  "usd": 0.231086,
  "source": "CoinGecko",
  "ts": "2026-07-03T19:08:41Z"
 },
 "TRB@Ethereum": {
  "usd": 15.77,
  "source": "CoinGecko",
  "ts": "2026-07-03T19:08:41Z"
 },
 "TRB_ETH@Ethereum": {
  "usd": 15.77,
  "source": "CoinGecko",
  "ts": "2026-07-03T19:08:41Z"
 },
 "UMA@Ethereum": {
  "usd": 0.392774,
  "source": "CoinGecko",
  "ts": "2026-07-03T19:08:41Z"
 },
 "tBTC@Ethereum": {
  "usd": 61928.0,
  "source": "CoinGecko",
  "ts": "2026-07-03T19:08:41Z"
 },
 "TBTC2@Arbitrum": {
  "usd": 61928.0,
  "source": "CoinGecko",
  "ts": "2026-07-03T19:08:41Z"
 },
 "LPT@Ethereum": {
  "usd": 1.62,
  "source": "CoinGecko",
  "ts": "2026-07-03T19:08:41Z"
 },
 "GLM@Ethereum": {
  "usd": 0.100995,
  "source": "CoinGecko",
  "ts": "2026-07-03T19:08:41Z"
 },
 "GLM_ETH@Ethereum": {
  "usd": 0.100995,
  "source": "CoinGecko",
  "ts": "2026-07-03T19:08:41Z"
 },
 "MILADY@Ethereum": {
  "usd": 6.921e-09,
  "source": "CoinGecko",
  "ts": "2026-07-03T19:08:41Z"
 },
 "WOJAK@Ethereum": {
  "usd": 1.237e-05,
  "source": "CoinGecko",
  "ts": "2026-07-03T19:08:41Z"
 },
 "GRASS@Solana": {
  "usd": 0.553634,
  "source": "CoinGecko",
  "ts": "2026-07-03T19:08:41Z"
 },
 "ETHX@Ethereum": {
  "usd": 1898.92,
  "source": "CoinGecko",
  "ts": "2026-07-03T19:08:41Z"
 },
 "ILV@Ethereum": {
  "usd": 3.11,
  "source": "CoinGecko",
  "ts": "2026-07-03T19:08:41Z"
 },
 "GODS@Ethereum": {
  "usd": 0.02531554,
  "source": "CoinGecko",
  "ts": "2026-07-03T19:08:41Z"
 },
 "PUFFER@Ethereum": {
  "usd": 0.01436024,
  "source": "CoinGecko",
  "ts": "2026-07-03T19:08:41Z"
 },
 "SWELL@Ethereum": {
  "usd": 0.00078044,
  "source": "CoinGecko",
  "ts": "2026-07-03T19:08:41Z"
 },
 "METIS@Ethereum": {
  "usd": 2.85,
  "source": "CoinGecko",
  "ts": "2026-07-03T19:08:41Z"
 },
 "ANKR@Ethereum": {
  "usd": 0.00365632,
  "source": "CoinGecko",
  "ts": "2026-07-03T19:08:41Z"
 },
 "TRAC@Ethereum": {
  "usd": 0.278465,
  "source": "CoinGecko",
  "ts": "2026-07-03T19:08:41Z"
 },
 "BIFI@Ethereum": {
  "usd": 38.35,
  "source": "CoinGecko",
  "ts": "2026-07-03T19:08:41Z"
 },
 "BIFI@Polygon": {
  "usd": 38.35,
  "source": "CoinGecko",
  "ts": "2026-07-03T19:08:41Z"
 },
 "SYN@Ethereum": {
  "usd": 0.470716,
  "source": "CoinGecko",
  "ts": "2026-07-03T19:08:41Z"
 },
 "GNS@Arbitrum": {
  "usd": 0.631325,
  "source": "CoinGecko",
  "ts": "2026-07-03T19:08:41Z"
 },
 "sAVAX@Avalanche": {
  "usd": 8.66,
  "source": "CoinGecko",
  "ts": "2026-07-03T19:08:41Z"
 },
 "LRC@Ethereum": {
  "usd": 0.01235685,
  "source": "CoinGecko",
  "ts": "2026-07-03T19:08:41Z"
 },
 "TAIKO@Ethereum": {
  "usd": 0.114252,
  "source": "CoinGecko",
  "ts": "2026-07-03T19:08:41Z"
 },
 "SCROLL@Ethereum": {
  "usd": 0.02968725,
  "source": "CoinGecko",
  "ts": "2026-07-03T19:08:41Z"
 },
 "GRAIL@Arbitrum": {
  "usd": 54.11,
  "source": "CoinGecko",
  "ts": "2026-07-03T19:08:41Z"
 },
 "DIA@Ethereum": {
  "usd": 0.110309,
  "source": "CoinGecko",
  "ts": "2026-07-03T19:08:41Z"
 },
 "OETH@Ethereum": {
  "usd": 1741.62,
  "source": "CoinGecko",
  "ts": "2026-07-03T19:08:41Z"
 },
 "QI@Avalanche": {
  "usd": 0.00120579,
  "source": "CoinGecko",
  "ts": "2026-07-03T19:08:41Z"
 },
 "STORJ@Ethereum": {
  "usd": 0.076352,
  "source": "CoinGecko",
  "ts": "2026-07-03T19:08:41Z"
 },
 "QUICK@Polygon": {
  "usd": 9.4,
  "source": "CoinGecko",
  "ts": "2026-07-03T19:08:41Z"
 },
 "NOT@Ethereum": {
  "usd": 0.00040104,
  "source": "CoinGecko",
  "ts": "2026-07-03T19:08:41Z"
 },
 "MPLX@Solana": {
  "usd": 0.03563339,
  "source": "CoinGecko",
  "ts": "2026-07-03T19:08:41Z"
 },
 "MOBILE@Solana": {
  "usd": 7.822e-05,
  "source": "CoinGecko",
  "ts": "2026-07-03T19:08:41Z"
 },
 "MNDE@Solana": {
  "usd": 0.01885339,
  "source": "CoinGecko",
  "ts": "2026-07-03T19:08:41Z"
 },
 "BAND@Ethereum": {
  "usd": 0.154572,
  "source": "CoinGecko",
  "ts": "2026-07-03T19:08:41Z"
 },
 "BAND_ETH@Ethereum": {
  "usd": 0.154572,
  "source": "CoinGecko",
  "ts": "2026-07-03T19:08:41Z"
 },
 "LAYER3@Ethereum": {
  "usd": 0.00616023,
  "source": "CoinGecko",
  "ts": "2026-07-03T19:08:41Z"
 },
 "XAUT@Ethereum": {
  "usd": 4161.24,
  "source": "CoinGecko",
  "ts": "2026-07-03T19:08:41Z"
 },
 "DODO@Ethereum": {
  "usd": 0.01887697,
  "source": "CoinGecko",
  "ts": "2026-07-03T19:08:41Z"
 },
 "GHST@Polygon": {
  "usd": 0.057922,
  "source": "CoinGecko",
  "ts": "2026-07-03T19:08:41Z"
 },
 "GHST2@Ethereum": {
  "usd": 0.057922,
  "source": "CoinGecko",
  "ts": "2026-07-03T19:08:41Z"
 },
 "CLOUD@Solana": {
  "usd": 0.0170625,
  "source": "CoinGecko",
  "ts": "2026-07-03T19:08:41Z"
 },
 "MOCHI@Base": {
  "usd": 8.67391e-07,
  "source": "CoinGecko",
  "ts": "2026-07-03T19:08:41Z"
 },
 "OHM@Ethereum": {
  "usd": 16.87,
  "source": "CoinGecko",
  "ts": "2026-07-03T19:08:41Z"
 },
 "PIXEL@Ethereum": {
  "usd": 0.00517592,
  "source": "CoinGecko",
  "ts": "2026-07-03T19:08:41Z"
 },
 "OLAS@Ethereum": {
  "usd": 0.02751011,
  "source": "CoinGecko",
  "ts": "2026-07-03T19:08:41Z"
 },
 "FLUX@Ethereum": {
  "usd": 0.04592553,
  "source": "CoinGecko",
  "ts": "2026-07-03T19:08:41Z"
 },
 "ACH@Ethereum": {
  "usd": 0.00452918,
  "source": "CoinGecko",
  "ts": "2026-07-03T19:08:41Z"
 },
 "AKT@Ethereum": {
  "usd": 0.652808,
  "source": "CoinGecko",
  "ts": "2026-07-03T19:08:41Z"
 },
 "XVS@BSC": {
  "usd": 2.54,
  "source": "CoinGecko",
  "ts": "2026-07-03T19:08:41Z"
 },
 "MPL@Ethereum": {
  "usd": 0.408715,
  "source": "CoinGecko",
  "ts": "2026-07-03T19:08:41Z"
 },
 "MANTA@Ethereum": {
  "usd": 0.061848,
  "source": "CoinGecko",
  "ts": "2026-07-03T19:08:41Z"
 },
 "ALT@Ethereum": {
  "usd": 0.00631069,
  "source": "CoinGecko",
  "ts": "2026-07-03T19:08:41Z"
 },
 "CELO@Ethereum": {
  "usd": 0.063722,
  "source": "CoinGecko",
  "ts": "2026-07-03T19:08:41Z"
 },
 "ZRC20@Ethereum": {
  "usd": 0.03692864,
  "source": "CoinGecko",
  "ts": "2026-07-03T19:08:41Z"
 },
 "IOTX@Ethereum": {
  "usd": 0.00290205,
  "source": "CoinGecko",
  "ts": "2026-07-03T19:08:41Z"
 },
 "rswETH@Ethereum": {
  "usd": 1570.26,
  "source": "CoinGecko",
  "ts": "2026-07-03T19:08:41Z"
 },
 "ALPACA@BSC": {
  "usd": 0.00046043,
  "source": "CoinGecko",
  "ts": "2026-07-03T19:08:41Z"
 },
 "CFG@Ethereum": {
  "usd": 0.201182,
  "source": "CoinGecko",
  "ts": "2026-07-03T19:08:41Z"
 },
 "CLANKER@Base": {
  "usd": 3.48e-06,
  "source": "CoinGecko",
  "ts": "2026-07-03T19:08:41Z"
 },
 "OG@Ethereum": {
  "usd": 2.48,
  "source": "CoinGecko",
  "ts": "2026-07-03T19:08:41Z"
 },
 "RARE@Ethereum": {
  "usd": 0.01253241,
  "source": "CoinGecko",
  "ts": "2026-07-03T19:08:41Z"
 },
 "CARV@Ethereum": {
  "usd": 0.0367997,
  "source": "CoinGecko",
  "ts": "2026-07-03T19:08:41Z"
 },
 "TLM@BSC": {
  "usd": 0.0019154,
  "source": "CoinGecko",
  "ts": "2026-07-03T19:08:41Z"
 },
 "TLM2@Ethereum": {
  "usd": 0.0019154,
  "source": "CoinGecko",
  "ts": "2026-07-03T19:08:41Z"
 },
 "RDNT@Arbitrum": {
  "usd": 0.00077237,
  "source": "CoinGecko",
  "ts": "2026-07-03T19:08:41Z"
 },
 "ZEREBRO@Solana": {
  "usd": 0.03921028,
  "source": "CoinGecko",
  "ts": "2026-07-03T19:08:41Z"
 },
 "ZEREBRO2@Ethereum": {
  "usd": 0.03921028,
  "source": "CoinGecko",
  "ts": "2026-07-03T19:08:41Z"
 },
 "ARC@Solana": {
  "usd": 0.080354,
  "source": "CoinGecko",
  "ts": "2026-07-03T19:08:41Z"
 },
 "ELON@Ethereum": {
  "usd": 3.1233e-08,
  "source": "CoinGecko",
  "ts": "2026-07-03T19:08:41Z"
 },
 "ELON2@BSC": {
  "usd": 3.1233e-08,
  "source": "CoinGecko",
  "ts": "2026-07-03T19:08:41Z"
 },
 "HONEY_HM@Solana": {
  "usd": 0.00155144,
  "source": "CoinGecko",
  "ts": "2026-07-03T19:08:41Z"
 },
 "HONEY_SOL@Solana": {
  "usd": 0.00155144,
  "source": "CoinGecko",
  "ts": "2026-07-03T19:08:41Z"
 },
 "ATLAS@Solana": {
  "usd": 0.00011609,
  "source": "CoinGecko",
  "ts": "2026-07-03T19:08:41Z"
 },
 "INTER@Ethereum": {
  "usd": 0.210218,
  "source": "CoinGecko",
  "ts": "2026-07-03T19:08:41Z"
 },
 "LAZIO@BSC": {
  "usd": 0.398914,
  "source": "CoinGecko",
  "ts": "2026-07-03T19:08:41Z"
 },
 "PORTO@BSC": {
  "usd": 0.45795,
  "source": "CoinGecko",
  "ts": "2026-07-03T19:08:41Z"
 },
 "MFER@Ethereum": {
  "usd": 0.00045121,
  "source": "CoinGecko",
  "ts": "2026-07-03T19:08:41Z"
 },
 "NORMIE@Base": {
  "usd": 6.7772e-11,
  "source": "CoinGecko",
  "ts": "2026-07-03T19:08:41Z"
 },
 "NORMIE2@Ethereum": {
  "usd": 6.7772e-11,
  "source": "CoinGecko",
  "ts": "2026-07-03T19:08:41Z"
 },
 "DEGENAI@Solana": {
  "usd": 0.00011549,
  "source": "CoinGecko",
  "ts": "2026-07-03T19:08:41Z"
 },
 "MX@Ethereum": {
  "usd": 1.66,
  "source": "CoinGecko",
  "ts": "2026-07-03T19:08:41Z"
 },
 "ALICE@Ethereum": {
  "usd": 0.124269,
  "source": "CoinGecko",
  "ts": "2026-07-03T19:08:41Z"
 },
 "BEAM@Ethereum": {
  "usd": 0.00145105,
  "source": "CoinGecko",
  "ts": "2026-07-03T19:08:41Z"
 },
 "YGG@Ethereum": {
  "usd": 0.02337822,
  "source": "CoinGecko",
  "ts": "2026-07-03T19:08:41Z"
 },
 "MC@Ethereum": {
  "usd": 0.01280658,
  "source": "CoinGecko",
  "ts": "2026-07-03T19:08:41Z"
 },
 "SANTOS@BSC": {
  "usd": 0.566518,
  "source": "CoinGecko",
  "ts": "2026-07-03T19:08:41Z"
 },
 "ALPINE@BSC": {
  "usd": 0.322455,
  "source": "CoinGecko",
  "ts": "2026-07-03T19:08:41Z"
 },
 "MASK@Ethereum": {
  "usd": 0.429239,
  "source": "CoinGecko",
  "ts": "2026-07-03T19:08:41Z"
 },
 "CYBER@Ethereum": {
  "usd": 0.362605,
  "source": "CoinGecko",
  "ts": "2026-07-03T19:08:41Z"
 },
 "AIOZ@Ethereum": {
  "usd": 0.056166,
  "source": "CoinGecko",
  "ts": "2026-07-03T19:08:41Z"
 },
 "ID@BSC": {
  "usd": 0.03700066,
  "source": "CoinGecko",
  "ts": "2026-07-03T19:08:41Z"
 },
 "ACT@Solana": {
  "usd": 0.00903583,
  "source": "CoinGecko",
  "ts": "2026-07-03T19:08:41Z"
 },
 "MYRO@Solana": {
  "usd": 0.00281126,
  "source": "CoinGecko",
  "ts": "2026-07-03T19:08:41Z"
 },
 "WEN@Solana": {
  "usd": 4.78e-06,
  "source": "CoinGecko",
  "ts": "2026-07-03T19:08:41Z"
 },
 "WEN@Ethereum": {
  "usd": 4.78e-06,
  "source": "CoinGecko",
  "ts": "2026-07-03T19:08:41Z"
 },
 "ANDY@Ethereum": {
  "usd": 0.00216407,
  "source": "CoinGecko",
  "ts": "2026-07-03T19:08:41Z"
 },
 "POOL@Ethereum": {
  "usd": 0.04228233,
  "source": "CoinGecko",
  "ts": "2026-07-03T19:08:41Z"
 },
 "TROLL@Solana": {
  "usd": 0.06334,
  "source": "CoinGecko",
  "ts": "2026-07-03T19:08:41Z"
 },
 "GIGA@Solana": {
  "usd": 0.0027068,
  "source": "CoinGecko",
  "ts": "2026-07-03T19:08:41Z"
 },
 "MAGA@Ethereum": {
  "usd": 0.02647547,
  "source": "CoinGecko",
  "ts": "2026-07-03T19:08:41Z"
 },
 "ACROSS@Ethereum": {
  "usd": 0.04288488,
  "source": "CoinGecko",
  "ts": "2026-07-03T19:08:41Z"
 },
 "USDM@Ethereum": {
  "usd": 1.001,
  "source": "CoinGecko",
  "ts": "2026-07-03T19:08:41Z"
 },
 "agEUR@Ethereum": {
  "usd": 1.14,
  "source": "CoinGecko",
  "ts": "2026-07-03T19:08:41Z"
 },
 "T@Ethereum": {
  "usd": 0.0035642,
  "source": "CoinGecko",
  "ts": "2026-07-03T19:08:41Z"
 },
 "HOP@Ethereum": {
  "usd": 0.0005379,
  "source": "CoinGecko",
  "ts": "2026-07-03T19:08:41Z"
 },
 "MELANIA@Solana": {
  "usd": 0.08247,
  "source": "CoinGecko",
  "ts": "2026-07-03T19:08:41Z"
 },
 "JONES@Arbitrum": {
  "usd": 0.098722,
  "source": "CoinGecko",
  "ts": "2026-07-03T19:08:41Z"
 },
 "MEMECORE@Ethereum": {
  "usd": 1.53,
  "source": "CoinGecko",
  "ts": "2026-07-03T19:08:41Z"
 },
 "RLC@Ethereum": {
  "usd": 0.304602,
  "source": "CoinGecko",
  "ts": "2026-07-03T19:08:41Z"
 },
 "RLC_ETH@Ethereum": {
  "usd": 0.304602,
  "source": "CoinGecko",
  "ts": "2026-07-03T19:08:41Z"
 },
 "BADGER@Ethereum": {
  "usd": 0.349377,
  "source": "CoinGecko",
  "ts": "2026-07-03T19:08:41Z"
 },
 "SPELL@Ethereum": {
  "usd": 9.125e-05,
  "source": "CoinGecko",
  "ts": "2026-07-03T19:08:41Z"
 },
 "REQ@Ethereum": {
  "usd": 0.055363,
  "source": "CoinGecko",
  "ts": "2026-07-03T19:08:41Z"
 },
 "PERP@Optimism": {
  "usd": 0.01858358,
  "source": "CoinGecko",
  "ts": "2026-07-03T19:08:41Z"
 },
 "ALCX@Ethereum": {
  "usd": 2.36,
  "source": "CoinGecko",
  "ts": "2026-07-03T19:08:41Z"
 },
 "PUNCH@Solana": {
  "usd": 3.3854e-08,
  "source": "CoinGecko",
  "ts": "2026-07-03T19:08:41Z"
 },
 "SLERF@Solana": {
  "usd": 0.01567266,
  "source": "CoinGecko",
  "ts": "2026-07-03T19:08:41Z"
 },
 "VVAIFU@Solana": {
  "usd": 0.00023427,
  "source": "CoinGecko",
  "ts": "2026-07-03T19:08:41Z"
 },
 "HARAMBE@Solana": {
  "usd": 1.051e-05,
  "source": "CoinGecko",
  "ts": "2026-07-03T19:08:41Z"
 },
 "FWOG@Solana": {
  "usd": 0.00482933,
  "source": "CoinGecko",
  "ts": "2026-07-03T19:08:41Z"
 },
 "KNINE@Solana": {
  "usd": 3.34497e-07,
  "source": "CoinGecko",
  "ts": "2026-07-03T19:08:41Z"
 },
 "JPEG@Ethereum": {
  "usd": 5.51e-06,
  "source": "CoinGecko",
  "ts": "2026-07-03T19:08:41Z"
 },
 "OMNI@Ethereum": {
  "usd": 0.525,
  "source": "CoinGecko",
  "ts": "2026-07-03T19:08:41Z"
 },
 "XBORG@Ethereum": {
  "usd": 0.01481578,
  "source": "CoinGecko",
  "ts": "2026-07-03T19:08:41Z"
 },
 "WILD@Ethereum": {
  "usd": 0.01944684,
  "source": "CoinGecko",
  "ts": "2026-07-03T19:08:41Z"
 },
 "ASR@Ethereum": {
  "usd": 0.861817,
  "source": "CoinGecko",
  "ts": "2026-07-03T19:08:41Z"
 },
 "XCAD@Ethereum": {
  "usd": 0.0001225,
  "source": "CoinGecko",
  "ts": "2026-07-03T19:08:41Z"
 },
 "HOOK@BSC": {
  "usd": 0.00521279,
  "source": "CoinGecko",
  "ts": "2026-07-03T19:08:41Z"
 },
 "AURORA@Ethereum": {
  "usd": 0.02651897,
  "source": "CoinGecko",
  "ts": "2026-07-03T19:08:41Z"
 },
 "SUPRA@Ethereum": {
  "usd": 0.00022855,
  "source": "CoinGecko",
  "ts": "2026-07-03T19:08:41Z"
 },
 "XYO@Ethereum": {
  "usd": 0.00323524,
  "source": "CoinGecko",
  "ts": "2026-07-03T19:08:41Z"
 },
 "LUMIA@Ethereum": {
  "usd": 0.128075,
  "source": "CoinGecko",
  "ts": "2026-07-03T19:08:41Z"
 },
 "LOOKS@Ethereum": {
  "usd": 0.00021636,
  "source": "CoinGecko",
  "ts": "2026-07-03T19:08:41Z"
 },
 "KWENTA@Optimism": {
  "usd": 3.9,
  "source": "CoinGecko",
  "ts": "2026-07-03T19:08:41Z"
 },
 "BSW@BSC": {
  "usd": 0.00032966,
  "source": "CoinGecko",
  "ts": "2026-07-03T19:08:41Z"
 },
 "UNFI@BSC": {
  "usd": 0.03863529,
  "source": "CoinGecko",
  "ts": "2026-07-03T19:08:41Z"
 },
 "TKO@BSC": {
  "usd": 0.04789346,
  "source": "CoinGecko",
  "ts": "2026-07-03T19:08:41Z"
 },
 "ggAVAX@Avalanche": {
  "usd": 0.03307068,
  "source": "CoinGecko",
  "ts": "2026-07-03T19:08:41Z"
 },
 "PYR@Ethereum": {
  "usd": 0.148082,
  "source": "CoinGecko",
  "ts": "2026-07-03T19:08:41Z"
 },
 "MODE@Ethereum": {
  "usd": 5.016e-05,
  "source": "CoinGecko",
  "ts": "2026-07-03T19:08:41Z"
 },
 "FUEL@Ethereum": {
  "usd": 0.0007148,
  "source": "CoinGecko",
  "ts": "2026-07-03T19:08:41Z"
 },
 "LSK@Ethereum": {
  "usd": 0.08953,
  "source": "CoinGecko",
  "ts": "2026-07-03T19:08:41Z"
 },
 "PLA@Ethereum": {
  "usd": 0.00085463,
  "source": "CoinGecko",
  "ts": "2026-07-03T19:08:41Z"
 },
 "HIGH@Ethereum": {
  "usd": 0.03717578,
  "source": "CoinGecko",
  "ts": "2026-07-03T19:08:41Z"
 },
 "VOXEL@Ethereum": {
  "usd": 0.00352112,
  "source": "CoinGecko",
  "ts": "2026-07-03T19:08:41Z"
 },
 "BTRST@Ethereum": {
  "usd": 0.058207,
  "source": "CoinGecko",
  "ts": "2026-07-03T19:08:41Z"
 },
 "POWR@Ethereum": {
  "usd": 0.04417737,
  "source": "CoinGecko",
  "ts": "2026-07-03T19:08:41Z"
 },
 "SUB@Ethereum": {
  "usd": 0.00018768,
  "source": "CoinGecko",
  "ts": "2026-07-03T19:08:41Z"
 },
 "MOBY@Arbitrum": {
  "usd": 0.00312973,
  "source": "CoinGecko",
  "ts": "2026-07-03T19:08:41Z"
 },
 "NOTIONAL@Arbitrum": {
  "usd": 0.00640744,
  "source": "CoinGecko",
  "ts": "2026-07-03T19:08:41Z"
 },
 "SAMO@Solana": {
  "usd": 0.00025286,
  "source": "CoinGecko",
  "ts": "2026-07-03T19:08:41Z"
 },
 "HXRO@Solana": {
  "usd": 0.00249142,
  "source": "CoinGecko",
  "ts": "2026-07-03T19:08:41Z"
 },
 "POLIS@Solana": {
  "usd": 0.00853287,
  "source": "CoinGecko",
  "ts": "2026-07-03T19:08:41Z"
 },
 "TSUKA@Ethereum": {
  "usd": 0.00090622,
  "source": "CoinGecko",
  "ts": "2026-07-03T19:08:41Z"
 },
 "IOT@Solana": {
  "usd": 3.967e-05,
  "source": "CoinGecko",
  "ts": "2026-07-03T19:08:41Z"
 },
 "DIMO@Polygon": {
  "usd": 0.00645223,
  "source": "CoinGecko",
  "ts": "2026-07-03T19:08:41Z"
 },
 "GRIFFAIN@Solana": {
  "usd": 0.00970961,
  "source": "CoinGecko",
  "ts": "2026-07-03T19:08:41Z"
 },
 "RETARDIO@Solana": {
  "usd": 0.00206757,
  "source": "CoinGecko",
  "ts": "2026-07-03T19:08:41Z"
 },
 "AKITA@Ethereum": {
  "usd": 3.244e-09,
  "source": "CoinGecko",
  "ts": "2026-07-03T19:08:41Z"
 },
 "ANON@Base": {
  "usd": 0.00166542,
  "source": "CoinGecko",
  "ts": "2026-07-03T19:08:41Z"
 },
 "PNG@Avalanche": {
  "usd": 0.02226166,
  "source": "CoinGecko",
  "ts": "2026-07-03T19:08:41Z"
 },
 "LUNA_AI@Solana": {
  "usd": 0.00479091,
  "source": "CoinGecko",
  "ts": "2026-07-03T19:08:41Z"
 },
 "LUNA_AI@Base": {
  "usd": 0.00479091,
  "source": "CoinGecko",
  "ts": "2026-07-03T19:08:41Z"
 },
 "BODEN@Solana": {
  "usd": 0.00094812,
  "source": "CoinGecko",
  "ts": "2026-07-03T19:08:41Z"
 },
 "BASED@Base": {
  "usd": 0.02234816,
  "source": "CoinGecko",
  "ts": "2026-07-03T19:08:41Z"
 },
 "CULT@Ethereum": {
  "usd": 6.44579e-07,
  "source": "CoinGecko",
  "ts": "2026-07-03T19:08:41Z"
 },
 "ANGLE@Ethereum": {
  "usd": 0.01605427,
  "source": "CoinGecko",
  "ts": "2026-07-03T19:08:41Z"
 },
 "COQ@Avalanche": {
  "usd": 7.8204e-08,
  "source": "CoinGecko",
  "ts": "2026-07-03T19:08:41Z"
 },
 "FREYSA@Ethereum": {
  "usd": 0.00308375,
  "source": "CoinGecko",
  "ts": "2026-07-03T19:08:41Z"
 },
 "SKI@Base": {
  "usd": 0.00610808,
  "source": "CoinGecko",
  "ts": "2026-07-03T19:08:41Z"
 },
 "MIGGLES@Base": {
  "usd": 0.00185378,
  "source": "CoinGecko",
  "ts": "2026-07-03T19:08:41Z"
 },
 "PAAL@Ethereum": {
  "usd": 0.00882171,
  "source": "CoinGecko",
  "ts": "2026-07-03T19:08:41Z"
 },
 "rsETH@Ethereum": {
  "usd": 1861.66,
  "source": "CoinGecko",
  "ts": "2026-07-03T19:08:41Z"
 },
 "MENCHESTER@Ethereum": {
  "usd": 1.004,
  "source": "CoinGecko",
  "ts": "2026-07-03T19:08:41Z"
 },
 "STEP@Solana": {
  "usd": 0.00014899,
  "source": "CoinGecko",
  "ts": "2026-07-03T19:08:41Z"
 },
 "ezETH@Ethereum": {
  "usd": 1872.2,
  "source": "CoinGecko",
  "ts": "2026-07-03T19:08:41Z"
 },
 "IPOR@Ethereum": {
  "usd": 0.00790322,
  "source": "CoinGecko",
  "ts": "2026-07-03T19:08:41Z"
 },
 "SPECTRA@Ethereum": {
  "usd": 0.00294288,
  "source": "CoinGecko",
  "ts": "2026-07-03T19:08:41Z"
 },
 "MNGO@Ethereum": {
  "usd": 0.02899611,
  "source": "CoinGecko",
  "ts": "2026-07-03T19:08:41Z"
 },
 "MNGO@Solana": {
  "usd": 0.02899611,
  "source": "CoinGecko",
  "ts": "2026-07-03T19:08:41Z"
 },
 "KIMBO@Avalanche": {
  "usd": 2.3e-06,
  "source": "CoinGecko",
  "ts": "2026-07-03T19:08:41Z"
 },
 "NATIX@Solana": {
  "usd": 8.702e-05,
  "source": "CoinGecko",
  "ts": "2026-07-03T19:08:41Z"
 },
 "GEOD@Polygon": {
  "usd": 0.226052,
  "source": "CoinGecko",
  "ts": "2026-07-03T19:08:41Z"
 },
 "REVV@Polygon": {
  "usd": 9.999e-05,
  "source": "CoinGecko",
  "ts": "2026-07-03T19:08:41Z"
 },
 "LAYER@Ethereum": {
  "usd": 0.887792,
  "source": "CoinGecko",
  "ts": "2026-07-03T19:08:41Z"
 },
 "EULER@Ethereum": {
  "usd": 1.049,
  "source": "CoinGecko",
  "ts": "2026-07-03T19:08:41Z"
 },
 "RAIL@Ethereum": {
  "usd": 2.05,
  "source": "CoinGecko",
  "ts": "2026-07-03T19:08:41Z"
 },
 "BERA@Ethereum": {
  "usd": 0.21726,
  "source": "CoinGecko",
  "ts": "2026-07-03T19:08:41Z"
 },
 "KEYCAT@Base": {
  "usd": 0.00043956,
  "source": "CoinGecko",
  "ts": "2026-07-03T19:08:41Z"
 },
 "WETH_ARB@Arbitrum": {
  "usd": 1737.2,
  "source": "CoinGecko",
  "ts": "2026-07-03T19:08:41Z"
 },
 "WETH_OP@Optimism": {
  "usd": 1737.2,
  "source": "CoinGecko",
  "ts": "2026-07-03T19:08:41Z"
 },
 "WETH_POL@Polygon": {
  "usd": 1737.2,
  "source": "CoinGecko",
  "ts": "2026-07-03T19:08:41Z"
 },
 "WETH_BSC@BSC": {
  "usd": 1737.2,
  "source": "CoinGecko",
  "ts": "2026-07-03T19:08:41Z"
 },
 "WETH_AVAX@Avalanche": {
  "usd": 1737.2,
  "source": "CoinGecko",
  "ts": "2026-07-03T19:08:41Z"
 },
 "2Z@Solana": {
  "usd": 0.067219,
  "source": "CoinGecko",
  "ts": "2026-07-03T19:08:41Z"
 },
 "ASTER@BSC": {
  "usd": 0.652418,
  "source": "CoinGecko",
  "ts": "2026-07-03T19:08:41Z"
 },
 "ATOM@Cosmos": {
  "usd": 1.6,
  "source": "CoinGecko",
  "ts": "2026-07-03T19:08:41Z"
 },
 "AUSD@Ethereum": {
  "usd": 0.999729,
  "source": "CoinGecko",
  "ts": "2026-07-03T19:08:41Z"
 },
 "BMX@Ethereum": {
  "usd": 0.32606,
  "source": "CoinGecko",
  "ts": "2026-07-03T19:08:41Z"
 },
 "BTSE@Ethereum": {
  "usd": 0.956416,
  "source": "CoinGecko",
  "ts": "2026-07-03T19:08:41Z"
 },
 "CHEEMS@BSC": {
  "usd": 4.86633e-07,
  "source": "CoinGecko",
  "ts": "2026-07-03T19:08:41Z"
 },
 "DEXE@Ethereum": {
  "usd": 23.37,
  "source": "CoinGecko",
  "ts": "2026-07-03T19:08:41Z"
 },
 "DOLA@Ethereum": {
  "usd": 0.995865,
  "source": "CoinGecko",
  "ts": "2026-07-03T19:08:41Z"
 },
 "FTM@Ethereum": {
  "usd": 0.03091421,
  "source": "CoinGecko",
  "ts": "2026-07-03T19:08:41Z"
 },
 "FTT@Ethereum": {
  "usd": 0.236306,
  "source": "CoinGecko",
  "ts": "2026-07-03T19:08:41Z"
 },
 "GNO@Ethereum": {
  "usd": 104.85,
  "source": "CoinGecko",
  "ts": "2026-07-03T19:08:41Z"
 },
 "GOMINING@Ethereum": {
  "usd": 0.271321,
  "source": "CoinGecko",
  "ts": "2026-07-03T19:08:41Z"
 },
 "HEX@Ethereum": {
  "usd": 0.00045817,
  "source": "CoinGecko",
  "ts": "2026-07-03T19:08:41Z"
 },
 "INJ@Ethereum": {
  "usd": 4.87,
  "source": "CoinGecko",
  "ts": "2026-07-03T19:08:41Z"
 },
 "JASMY@Ethereum": {
  "usd": 0.00458572,
  "source": "CoinGecko",
  "ts": "2026-07-03T19:08:41Z"
 },
 "KTA@Base": {
  "usd": 0.141934,
  "source": "CoinGecko",
  "ts": "2026-07-03T19:08:41Z"
 },
 "LEO@Ethereum": {
  "usd": 9.15,
  "source": "CoinGecko",
  "ts": "2026-07-03T19:08:41Z"
 },
 "LSETH@Ethereum": {
  "usd": 1994.54,
  "source": "CoinGecko",
  "ts": "2026-07-03T19:08:41Z"
 },
 "NEXO@Ethereum": {
  "usd": 0.761525,
  "source": "CoinGecko",
  "ts": "2026-07-03T19:08:41Z"
 },
 "NXPC@Ethereum": {
  "usd": 0.277496,
  "source": "CoinGecko",
  "ts": "2026-07-03T19:08:41Z"
 },
 "QNT@Ethereum": {
  "usd": 68.19,
  "source": "CoinGecko",
  "ts": "2026-07-03T19:08:41Z"
 },
 "RLB@Ethereum": {
  "usd": 0.063356,
  "source": "CoinGecko",
  "ts": "2026-07-03T19:08:41Z"
 },
 "RLUSD@Ethereum": {
  "usd": 0.999888,
  "source": "CoinGecko",
  "ts": "2026-07-03T19:08:41Z"
 },
 "RSR@Ethereum": {
  "usd": 0.00123909,
  "source": "CoinGecko",
  "ts": "2026-07-03T19:08:41Z"
 },
 "SFP@BSC": {
  "usd": 0.223928,
  "source": "CoinGecko",
  "ts": "2026-07-03T19:08:41Z"
 },
 "SHFL@Ethereum": {
  "usd": 0.253552,
  "source": "CoinGecko",
  "ts": "2026-07-03T19:08:41Z"
 },
 "SKYAI@BSC": {
  "usd": 0.074893,
  "source": "CoinGecko",
  "ts": "2026-07-03T19:08:41Z"
 },
 "SOSO@Base": {
  "usd": 0.297958,
  "source": "CoinGecko",
  "ts": "2026-07-03T19:08:41Z"
 },
 "TEL@Polygon": {
  "usd": 0.00236953,
  "source": "CoinGecko",
  "ts": "2026-07-03T19:08:41Z"
 },
 "TIBBIR@Base": {
  "usd": 0.105537,
  "source": "CoinGecko",
  "ts": "2026-07-03T19:08:41Z"
 },
 "TUSD@Ethereum": {
  "usd": 0.998505,
  "source": "CoinGecko",
  "ts": "2026-07-03T19:08:41Z"
 },
 "TWT@BSC": {
  "usd": 0.345865,
  "source": "CoinGecko",
  "ts": "2026-07-03T19:08:41Z"
 },
 "USDD@Ethereum": {
  "usd": 0.998458,
  "source": "CoinGecko",
  "ts": "2026-07-03T19:08:41Z"
 },
 "USDG@Ethereum": {
  "usd": 0.999963,
  "source": "CoinGecko",
  "ts": "2026-07-03T19:08:41Z"
 },
 "VVV@Base": {
  "usd": 13.56,
  "source": "CoinGecko",
  "ts": "2026-07-03T19:08:41Z"
 },
 "WBETH@BSC": {
  "usd": 1912.77,
  "source": "CoinGecko",
  "ts": "2026-07-03T19:08:41Z"
 },
 "WBNB@BSC": {
  "usd": 567.53,
  "source": "CoinGecko",
  "ts": "2026-07-03T19:08:41Z"
 },
 "XCN@Ethereum": {
  "usd": 0.00392871,
  "source": "CoinGecko",
  "ts": "2026-07-03T19:08:41Z"
 },
 "XLM@Stellar": {
  "usd": 0.202415,
  "source": "CoinGecko",
  "ts": "2026-07-03T19:08:41Z"
 },
 "YZY@Solana": {
  "usd": 0.293578,
  "source": "CoinGecko",
  "ts": "2026-07-03T19:08:41Z"
 },
 "ZBCN@Solana": {
  "usd": 0.00233423,
  "source": "CoinGecko",
  "ts": "2026-07-03T19:08:41Z"
 },
 "ZIG@Ethereum": {
  "usd": 0.04722976,
  "source": "CoinGecko",
  "ts": "2026-07-03T19:08:41Z"
 },
 "sUSDS@Ethereum": {
  "usd": 1.1,
  "source": "CoinGecko",
  "ts": "2026-07-03T19:08:41Z"
 },
 "WMATIC@Polygon": {
  "usd": 0.073085,
  "source": "CoinGecko",
  "ts": "2026-07-03T19:08:41Z"
 },
 "MIM@Avalanche": {
  "usd": 0.145661,
  "source": "CoinGecko",
  "ts": "2026-07-03T19:08:41Z"
 },
 "MIMATIC@Polygon": {
  "usd": 0.992356,
  "source": "CoinGecko",
  "ts": "2026-07-03T19:08:41Z"
 },
 "TIME@Avalanche": {
  "usd": 0.01174408,
  "source": "CoinGecko",
  "ts": "2026-07-03T19:08:41Z"
 },
 "USDTE@Avalanche": {
  "usd": 0.998632,
  "source": "CoinGecko",
  "ts": "2026-07-03T19:08:41Z"
 },
 "WAVAX@Avalanche": {
  "usd": 6.87,
  "source": "CoinGecko",
  "ts": "2026-07-03T19:08:41Z"
 },
 "BTCB@BSC": {
  "usd": 62106.0,
  "source": "CoinGecko",
  "ts": "2026-07-03T19:08:41Z"
 },
 "BUSD@BSC": {
  "usd": 0.997765,
  "source": "CoinGecko",
  "ts": "2026-07-03T19:08:41Z"
 },
 "ENJ@Ethereum": {
  "usd": 0.03022337,
  "source": "CoinGecko",
  "ts": "2026-07-03T19:08:41Z"
 },
 "FISH@Polygon": {
  "usd": 0.00527139,
  "source": "CoinGecko",
  "ts": "2026-07-03T19:08:41Z"
 },
 "MELT@Avalanche": {
  "usd": 0.00018525,
  "source": "CoinGecko",
  "ts": "2026-07-03T19:08:41Z"
 },
 "RAI@Ethereum": {
  "usd": 2.04,
  "source": "CoinGecko",
  "ts": "2026-07-03T19:08:41Z"
 },
 "YAK@Avalanche": {
  "usd": 39.15,
  "source": "CoinGecko",
  "ts": "2026-07-03T19:08:41Z"
 },
 "ZRX@Ethereum": {
  "usd": 0.084994,
  "source": "CoinGecko",
  "ts": "2026-07-03T19:08:41Z"
 },
 "ADA@BSC": {
  "usd": 0.179715,
  "source": "CoinGecko",
  "ts": "2026-07-03T19:08:41Z"
 },
 "ADDY@Polygon": {
  "usd": 0.00685582,
  "source": "CoinGecko",
  "ts": "2026-07-03T19:08:41Z"
 },
 "AMP@Ethereum": {
  "usd": 0.00045286,
  "source": "CoinGecko",
  "ts": "2026-07-03T19:08:41Z"
 },
 "BNT@Ethereum": {
  "usd": 0.268586,
  "source": "CoinGecko",
  "ts": "2026-07-03T19:08:41Z"
 },
 "BOND@Ethereum": {
  "usd": 0.01735285,
  "source": "CoinGecko",
  "ts": "2026-07-03T19:08:41Z"
 },
 "DOT@BSC": {
  "usd": 0.882511,
  "source": "CoinGecko",
  "ts": "2026-07-03T19:08:41Z"
 },
 "DPX@Arbitrum": {
  "usd": 0.717025,
  "source": "CoinGecko",
  "ts": "2026-07-03T19:08:41Z"
 },
 "HELMET@BSC": {
  "usd": 0.00192137,
  "source": "CoinGecko",
  "ts": "2026-07-03T19:08:41Z"
 },
 "KLO@Avalanche": {
  "usd": 0.00060454,
  "source": "CoinGecko",
  "ts": "2026-07-03T19:08:41Z"
 },
 "LTC@BSC": {
  "usd": 44.07,
  "source": "CoinGecko",
  "ts": "2026-07-03T19:08:41Z"
 },
 "MBOX@BSC": {
  "usd": 0.00118032,
  "source": "CoinGecko",
  "ts": "2026-07-03T19:08:41Z"
 },
 "PEFI@Avalanche": {
  "usd": 0.00154519,
  "source": "CoinGecko",
  "ts": "2026-07-03T19:08:41Z"
 },
 "PTP@Avalanche": {
  "usd": 4.602e-05,
  "source": "CoinGecko",
  "ts": "2026-07-03T19:08:41Z"
 },
 "REN@Ethereum": {
  "usd": 0.00343209,
  "source": "CoinGecko",
  "ts": "2026-07-03T19:08:41Z"
 },
 "RGT@Ethereum": {
  "usd": 0.02235785,
  "source": "CoinGecko",
  "ts": "2026-07-03T19:08:41Z"
 },
 "SNOB@Avalanche": {
  "usd": 0.00029415,
  "source": "CoinGecko",
  "ts": "2026-07-03T19:08:41Z"
 },
 "SX@Polygon": {
  "usd": 0.01477247,
  "source": "CoinGecko",
  "ts": "2026-07-03T19:08:41Z"
 },
 "SXP@BSC": {
  "usd": 9.989e-05,
  "source": "CoinGecko",
  "ts": "2026-07-03T19:08:41Z"
 },
 "TUS@Avalanche": {
  "usd": 2.15e-06,
  "source": "CoinGecko",
  "ts": "2026-07-03T19:08:41Z"
 },
 "USTC@BSC": {
  "usd": 0.00568156,
  "source": "CoinGecko",
  "ts": "2026-07-03T19:08:41Z"
 },
 "VSO@Avalanche": {
  "usd": 0.00016051,
  "source": "CoinGecko",
  "ts": "2026-07-03T19:08:41Z"
 },
 "XAVA@Avalanche": {
  "usd": 0.292551,
  "source": "CoinGecko",
  "ts": "2026-07-03T19:08:41Z"
 },
 "XRP@BSC": {
  "usd": 1.13,
  "source": "CoinGecko",
  "ts": "2026-07-03T19:08:41Z"
 },
 "AGA@Polygon": {
  "usd": 0.03869057,
  "source": "CoinGecko",
  "ts": "2026-07-03T19:08:41Z"
 },
 "AGAR@Polygon": {
  "usd": 10.17,
  "source": "CoinGecko",
  "ts": "2026-07-03T19:08:41Z"
 },
 "ALPHA@BSC": {
  "usd": 0.00056089,
  "source": "CoinGecko",
  "ts": "2026-07-03T19:08:41Z"
 },
 "AVE@Avalanche": {
  "usd": 2.285e-05,
  "source": "CoinGecko",
  "ts": "2026-07-03T19:08:41Z"
 },
 "BAKE@BSC": {
  "usd": 0.00075191,
  "source": "CoinGecko",
  "ts": "2026-07-03T19:08:41Z"
 },
 "BANANA@BSC": {
  "usd": 1.4026e-08,
  "source": "CoinGecko",
  "ts": "2026-07-03T19:08:41Z"
 },
 "BCH@BSC": {
  "usd": 230.59,
  "source": "CoinGecko",
  "ts": "2026-07-03T19:08:41Z"
 },
 "BSCX@BSC": {
  "usd": 2.71,
  "source": "CoinGecko",
  "ts": "2026-07-03T19:08:41Z"
 },
 "BTCST@BSC": {
  "usd": 0.00863565,
  "source": "CoinGecko",
  "ts": "2026-07-03T19:08:41Z"
 },
 "BURGER@BSC": {
  "usd": 0.00056893,
  "source": "CoinGecko",
  "ts": "2026-07-03T19:08:41Z"
 },
 "CEL@Ethereum": {
  "usd": 0.01165316,
  "source": "CoinGecko",
  "ts": "2026-07-03T19:08:41Z"
 },
 "CELR@Arbitrum": {
  "usd": 0.00193478,
  "source": "CoinGecko",
  "ts": "2026-07-03T19:08:41Z"
 },
 "CRA@Avalanche": {
  "usd": 9.552e-05,
  "source": "CoinGecko",
  "ts": "2026-07-03T19:08:41Z"
 },
 "CRAFT@Avalanche": {
  "usd": 0.00018992,
  "source": "CoinGecko",
  "ts": "2026-07-03T19:08:41Z"
 },
 "DCAU@Avalanche": {
  "usd": 0.178719,
  "source": "CoinGecko",
  "ts": "2026-07-03T19:08:41Z"
 },
 "DOGE@BSC": {
  "usd": 0.076701,
  "source": "CoinGecko",
  "ts": "2026-07-03T19:08:41Z"
 },
 "DXD@Arbitrum": {
  "usd": 10.87,
  "source": "CoinGecko",
  "ts": "2026-07-03T19:08:41Z"
 },
 "EOS@BSC": {
  "usd": 0.127661,
  "source": "CoinGecko",
  "ts": "2026-07-03T19:08:41Z"
 },
 "EPS@BSC": {
  "usd": 0.0126903,
  "source": "CoinGecko",
  "ts": "2026-07-03T19:08:41Z"
 },
 "FIL@BSC": {
  "usd": 0.799119,
  "source": "CoinGecko",
  "ts": "2026-07-03T19:08:41Z"
 },
 "FIRE@Avalanche": {
  "usd": 0.092126,
  "source": "CoinGecko",
  "ts": "2026-07-03T19:08:41Z"
 },
 "FRONT@BSC": {
  "usd": 0.01255743,
  "source": "CoinGecko",
  "ts": "2026-07-03T19:08:41Z"
 },
 "FUEL@BSC": {
  "usd": 9.22,
  "source": "CoinGecko",
  "ts": "2026-07-03T19:08:41Z"
 },
 "GOHM@Avalanche": {
  "usd": 4543.82,
  "source": "CoinGecko",
  "ts": "2026-07-03T19:08:41Z"
 },
 "HERO@BSC": {
  "usd": 0.00043224,
  "source": "CoinGecko",
  "ts": "2026-07-03T19:08:41Z"
 },
 "HUSKY@Avalanche": {
  "usd": 1.558e-09,
  "source": "CoinGecko",
  "ts": "2026-07-03T19:08:41Z"
 },
 "IGG@Polygon": {
  "usd": 2.945e-05,
  "source": "CoinGecko",
  "ts": "2026-07-03T19:08:41Z"
 },
 "IME@Avalanche": {
  "usd": 2.22852e-07,
  "source": "CoinGecko",
  "ts": "2026-07-03T19:08:41Z"
 },
 "KNCL@Ethereum": {
  "usd": 0.11114,
  "source": "CoinGecko",
  "ts": "2026-07-03T19:08:41Z"
 },
 "LYD@Avalanche": {
  "usd": 5.347e-05,
  "source": "CoinGecko",
  "ts": "2026-07-03T19:08:41Z"
 },
 "MATH@Arbitrum": {
  "usd": 0.0238876,
  "source": "CoinGecko",
  "ts": "2026-07-03T19:08:41Z"
 },
 "MCB@Arbitrum": {
  "usd": 1.88,
  "source": "CoinGecko",
  "ts": "2026-07-03T19:08:41Z"
 },
 "MUST@Polygon": {
  "usd": 0.259608,
  "source": "CoinGecko",
  "ts": "2026-07-03T19:08:41Z"
 },
 "O3@BSC": {
  "usd": 0.00131913,
  "source": "CoinGecko",
  "ts": "2026-07-03T19:08:41Z"
 },
 "OM@Polygon": {
  "usd": 0.066603,
  "source": "CoinGecko",
  "ts": "2026-07-03T19:08:41Z"
 },
 "OMG@Ethereum": {
  "usd": 0.04574684,
  "source": "CoinGecko",
  "ts": "2026-07-03T19:08:41Z"
 },
 "ORN@Ethereum": {
  "usd": 0.0257458,
  "source": "CoinGecko",
  "ts": "2026-07-03T19:08:41Z"
 },
 "PREMIA@Arbitrum": {
  "usd": 0.01734527,
  "source": "CoinGecko",
  "ts": "2026-07-03T19:08:41Z"
 },
 "QI@Polygon": {
  "usd": 0.00456312,
  "source": "CoinGecko",
  "ts": "2026-07-03T19:08:41Z"
 },
 "RDPX@Arbitrum": {
  "usd": 0.473145,
  "source": "CoinGecko",
  "ts": "2026-07-03T19:08:41Z"
 },
 "REEF@BSC": {
  "usd": 5.504e-05,
  "source": "CoinGecko",
  "ts": "2026-07-03T19:08:41Z"
 },
 "SPORE@Avalanche": {
  "usd": 7.017e-12,
  "source": "CoinGecko",
  "ts": "2026-07-03T19:08:41Z"
 },
 "THOR@Avalanche": {
  "usd": 0.00087148,
  "source": "CoinGecko",
  "ts": "2026-07-03T19:08:41Z"
 },
 "TOKE@Ethereum": {
  "usd": 0.03240694,
  "source": "CoinGecko",
  "ts": "2026-07-03T19:08:41Z"
 },
 "VAI@BSC": {
  "usd": 1.001,
  "source": "CoinGecko",
  "ts": "2026-07-03T19:08:41Z"
 },
 "WEGLD@BSC": {
  "usd": 2.72,
  "source": "CoinGecko",
  "ts": "2026-07-03T19:08:41Z"
 },
 "WOLF@Polygon": {
  "usd": 2.5774e-08,
  "source": "CoinGecko",
  "ts": "2026-07-03T19:08:41Z"
 },
 "0XBTC@Ethereum": {
  "usd": 0.02796854,
  "source": "CoinGecko",
  "ts": "2026-07-03T19:08:41Z"
 },
 "ADX@Ethereum": {
  "usd": 0.051512,
  "source": "CoinGecko",
  "ts": "2026-07-03T19:08:41Z"
 },
 "ALEPH@Ethereum": {
  "usd": 0.01076422,
  "source": "CoinGecko",
  "ts": "2026-07-03T19:08:41Z"
 },
 "AMPL@Ethereum": {
  "usd": 1.29,
  "source": "CoinGecko",
  "ts": "2026-07-03T19:08:41Z"
 },
 "ANY@Polygon": {
  "usd": 0.491828,
  "source": "CoinGecko",
  "ts": "2026-07-03T19:08:41Z"
 },
 "ARV@BSC": {
  "usd": 1.78e-06,
  "source": "CoinGecko",
  "ts": "2026-07-03T19:08:41Z"
 },
 "AUTO@BSC": {
  "usd": 1.94,
  "source": "CoinGecko",
  "ts": "2026-07-03T19:08:41Z"
 },
 "AVAI@Avalanche": {
  "usd": 0.428459,
  "source": "CoinGecko",
  "ts": "2026-07-03T19:08:41Z"
 },
 "AVME@Avalanche": {
  "usd": 0.00020087,
  "source": "CoinGecko",
  "ts": "2026-07-03T19:08:41Z"
 },
 "AVXT@Avalanche": {
  "usd": 9.98e-06,
  "source": "CoinGecko",
  "ts": "2026-07-03T19:08:41Z"
 },
 "BAC@Ethereum": {
  "usd": 0.00285394,
  "source": "CoinGecko",
  "ts": "2026-07-03T19:08:41Z"
 },
 "BDO@BSC": {
  "usd": 0.00105807,
  "source": "CoinGecko",
  "ts": "2026-07-03T19:08:41Z"
 },
 "BELT@BSC": {
  "usd": 0.02900003,
  "source": "CoinGecko",
  "ts": "2026-07-03T19:08:41Z"
 },
 "BETH@BSC": {
  "usd": 1872.04,
  "source": "CoinGecko",
  "ts": "2026-07-03T19:08:41Z"
 },
 "BOOFI@Avalanche": {
  "usd": 0.00079257,
  "source": "CoinGecko",
  "ts": "2026-07-03T19:08:41Z"
 },
 "BRY@BSC": {
  "usd": 0.01085425,
  "source": "CoinGecko",
  "ts": "2026-07-03T19:08:41Z"
 },
 "BSCPAD@BSC": {
  "usd": 0.00377907,
  "source": "CoinGecko",
  "ts": "2026-07-03T19:08:41Z"
 },
 "BTCB@Avalanche": {
  "usd": 62171.0,
  "source": "CoinGecko",
  "ts": "2026-07-03T19:08:41Z"
 },
 "BUNNY@BSC": {
  "usd": 0.01452875,
  "source": "CoinGecko",
  "ts": "2026-07-03T19:08:41Z"
 },
 "C98@BSC": {
  "usd": 0.01339577,
  "source": "CoinGecko",
  "ts": "2026-07-03T19:08:41Z"
 },
 "CAP@Arbitrum": {
  "usd": 0.02017484,
  "source": "CoinGecko",
  "ts": "2026-07-03T19:08:41Z"
 },
 "CGG@BSC": {
  "usd": 0.00095891,
  "source": "CoinGecko",
  "ts": "2026-07-03T19:08:41Z"
 },
 "CHESS@BSC": {
  "usd": 0.00014228,
  "source": "CoinGecko",
  "ts": "2026-07-03T19:08:41Z"
 },
 "COOK@Avalanche": {
  "usd": 5.758e-05,
  "source": "CoinGecko",
  "ts": "2026-07-03T19:08:41Z"
 },
 "COTI@Ethereum": {
  "usd": 0.00874895,
  "source": "CoinGecko",
  "ts": "2026-07-03T19:08:41Z"
 },
 "CREAM@Ethereum": {
  "usd": 0.484833,
  "source": "CoinGecko",
  "ts": "2026-07-03T19:08:41Z"
 },
 "CTSI@Ethereum": {
  "usd": 0.02351707,
  "source": "CoinGecko",
  "ts": "2026-07-03T19:08:41Z"
 },
 "CTX@Ethereum": {
  "usd": 0.300008,
  "source": "CoinGecko",
  "ts": "2026-07-03T19:08:41Z"
 },
 "CWS@BSC": {
  "usd": 0.00884762,
  "source": "CoinGecko",
  "ts": "2026-07-03T19:08:41Z"
 },
 "DEXT@Ethereum": {
  "usd": 0.115249,
  "source": "CoinGecko",
  "ts": "2026-07-03T19:08:41Z"
 },
 "DOG@Arbitrum": {
  "usd": 0.00036446,
  "source": "CoinGecko",
  "ts": "2026-07-03T19:08:41Z"
 },
 "DOME@BSC": {
  "usd": 2.53e-06,
  "source": "CoinGecko",
  "ts": "2026-07-03T19:08:41Z"
 },
 "DPI@Ethereum": {
  "usd": 39.52,
  "source": "CoinGecko",
  "ts": "2026-07-03T19:08:41Z"
 },
 "DYP@Avalanche": {
  "usd": 0.00174843,
  "source": "CoinGecko",
  "ts": "2026-07-03T19:08:41Z"
 },
 "EDEN@Ethereum": {
  "usd": 0.0017113,
  "source": "CoinGecko",
  "ts": "2026-07-03T19:08:41Z"
 },
 "EGG@Avalanche": {
  "usd": 0.00017239,
  "source": "CoinGecko",
  "ts": "2026-07-03T19:08:41Z"
 },
 "EZ@BSC": {
  "usd": 0.00079959,
  "source": "CoinGecko",
  "ts": "2026-07-03T19:08:41Z"
 },
 "FARM@Ethereum": {
  "usd": 5.41,
  "source": "CoinGecko",
  "ts": "2026-07-03T19:08:41Z"
 },
 "FEI@Ethereum": {
  "usd": 1.002,
  "source": "CoinGecko",
  "ts": "2026-07-03T19:08:41Z"
 },
 "FINE@BSC": {
  "usd": 0.00021643,
  "source": "CoinGecko",
  "ts": "2026-07-03T19:08:41Z"
 },
 "FODL@Ethereum": {
  "usd": 0.00028574,
  "source": "CoinGecko",
  "ts": "2026-07-03T19:08:41Z"
 },
 "FUSE@Ethereum": {
  "usd": 0.00314914,
  "source": "CoinGecko",
  "ts": "2026-07-03T19:08:41Z"
 },
 "GAJ@Polygon": {
  "usd": 0.00233674,
  "source": "CoinGecko",
  "ts": "2026-07-03T19:08:41Z"
 },
 "GB@Avalanche": {
  "usd": 0.00259596,
  "source": "CoinGecko",
  "ts": "2026-07-03T19:08:41Z"
 },
 "GUSD@Ethereum": {
  "usd": 0.999519,
  "source": "CoinGecko",
  "ts": "2026-07-03T19:08:41Z"
 },
 "H2O@Avalanche": {
  "usd": 0.00037376,
  "source": "CoinGecko",
  "ts": "2026-07-03T19:08:41Z"
 },
 "IFARM@Polygon": {
  "usd": 9.48,
  "source": "CoinGecko",
  "ts": "2026-07-03T19:08:41Z"
 },
 "IOTX@BSC": {
  "usd": 0.00291686,
  "source": "CoinGecko",
  "ts": "2026-07-03T19:08:41Z"
 },
 "ISA@Avalanche": {
  "usd": 1.5076e-07,
  "source": "CoinGecko",
  "ts": "2026-07-03T19:08:41Z"
 },
 "JGN@BSC": {
  "usd": 0.00113018,
  "source": "CoinGecko",
  "ts": "2026-07-03T19:08:41Z"
 },
 "KEEP@Ethereum": {
  "usd": 0.01817824,
  "source": "CoinGecko",
  "ts": "2026-07-03T19:08:41Z"
 },
 "KP3R@Ethereum": {
  "usd": 0.913998,
  "source": "CoinGecko",
  "ts": "2026-07-03T19:08:41Z"
 },
 "KRILL@Polygon": {
  "usd": 0.0004648,
  "source": "CoinGecko",
  "ts": "2026-07-03T19:08:41Z"
 },
 "KUN@BSC": {
  "usd": 0.00365504,
  "source": "CoinGecko",
  "ts": "2026-07-03T19:08:41Z"
 },
 "LINA@BSC": {
  "usd": 1.015e-05,
  "source": "CoinGecko",
  "ts": "2026-07-03T19:08:41Z"
 },
 "LTO@BSC": {
  "usd": 0.00143239,
  "source": "CoinGecko",
  "ts": "2026-07-03T19:08:41Z"
 },
 "MCRN@BSC": {
  "usd": 0.00308404,
  "source": "CoinGecko",
  "ts": "2026-07-03T19:08:41Z"
 },
 "MLN@Ethereum": {
  "usd": 1.41,
  "source": "CoinGecko",
  "ts": "2026-07-03T19:08:41Z"
 },
 "MONA@Polygon": {
  "usd": 35.48,
  "source": "CoinGecko",
  "ts": "2026-07-03T19:08:41Z"
 },
 "MTA@Ethereum": {
  "usd": 0.03206164,
  "source": "CoinGecko",
  "ts": "2026-07-03T19:08:41Z"
 },
 "NRV@BSC": {
  "usd": 0.00043667,
  "source": "CoinGecko",
  "ts": "2026-07-03T19:08:41Z"
 },
 "NU@Ethereum": {
  "usd": 0.01154028,
  "source": "CoinGecko",
  "ts": "2026-07-03T19:08:41Z"
 },
 "OGN@Ethereum": {
  "usd": 0.01571795,
  "source": "CoinGecko",
  "ts": "2026-07-03T19:08:41Z"
 },
 "ONT@BSC": {
  "usd": 0.04456359,
  "source": "CoinGecko",
  "ts": "2026-07-03T19:08:41Z"
 },
 "PERL@BSC": {
  "usd": 9.42e-05,
  "source": "CoinGecko",
  "ts": "2026-07-03T19:08:41Z"
 },
 "PLOT@Polygon": {
  "usd": 0.00283961,
  "source": "CoinGecko",
  "ts": "2026-07-03T19:08:41Z"
 },
 "PNK@Ethereum": {
  "usd": 0.00836506,
  "source": "CoinGecko",
  "ts": "2026-07-03T19:08:41Z"
 },
 "POLY@Ethereum": {
  "usd": 0.0129433,
  "source": "CoinGecko",
  "ts": "2026-07-03T19:08:41Z"
 },
 "POTS@BSC": {
  "usd": 0.00320891,
  "source": "CoinGecko",
  "ts": "2026-07-03T19:08:41Z"
 },
 "RACA@BSC": {
  "usd": 1.306e-05,
  "source": "CoinGecko",
  "ts": "2026-07-03T19:08:41Z"
 },
 "RAMP@BSC": {
  "usd": 0.01611537,
  "source": "CoinGecko",
  "ts": "2026-07-03T19:08:41Z"
 },
 "RARI@Ethereum": {
  "usd": 0.093967,
  "source": "CoinGecko",
  "ts": "2026-07-03T19:08:41Z"
 },
 "RENBTC@Ethereum": {
  "usd": 13897.05,
  "source": "CoinGecko",
  "ts": "2026-07-03T19:08:41Z"
 },
 "REP@Ethereum": {
  "usd": 0.832613,
  "source": "CoinGecko",
  "ts": "2026-07-03T19:08:41Z"
 },
 "ROCO@Avalanche": {
  "usd": 0.01482411,
  "source": "CoinGecko",
  "ts": "2026-07-03T19:08:41Z"
 },
 "ROOK@Ethereum": {
  "usd": 0.064405,
  "source": "CoinGecko",
  "ts": "2026-07-03T19:08:41Z"
 },
 "ROUTE@Polygon": {
  "usd": 0.0372999,
  "source": "CoinGecko",
  "ts": "2026-07-03T19:08:41Z"
 },
 "SDT@Ethereum": {
  "usd": 0.086289,
  "source": "CoinGecko",
  "ts": "2026-07-03T19:08:41Z"
 },
 "SFUND@BSC": {
  "usd": 0.00318321,
  "source": "CoinGecko",
  "ts": "2026-07-03T19:08:41Z"
 },
 "SHIBX@Avalanche": {
  "usd": 2.32e-06,
  "source": "CoinGecko",
  "ts": "2026-07-03T19:08:41Z"
 },
 "SOS@Ethereum": {
  "usd": 1.684e-09,
  "source": "CoinGecko",
  "ts": "2026-07-03T19:08:41Z"
 },
 "SRM@Ethereum": {
  "usd": 0.00751391,
  "source": "CoinGecko",
  "ts": "2026-07-03T19:08:41Z"
 },
 "STARL@Ethereum": {
  "usd": 1.05639e-07,
  "source": "CoinGecko",
  "ts": "2026-07-03T19:08:41Z"
 },
 "SUPER@Ethereum": {
  "usd": 0.090373,
  "source": "CoinGecko",
  "ts": "2026-07-03T19:08:41Z"
 },
 "SUSD@Arbitrum": {
  "usd": 0.231948,
  "source": "CoinGecko",
  "ts": "2026-07-03T19:08:41Z"
 },
 "SWPR@Arbitrum": {
  "usd": 0.00558702,
  "source": "CoinGecko",
  "ts": "2026-07-03T19:08:41Z"
 },
 "TITAN@Polygon": {
  "usd": 1.62e-09,
  "source": "CoinGecko",
  "ts": "2026-07-03T19:08:41Z"
 },
 "TPT@BSC": {
  "usd": 0.00566245,
  "source": "CoinGecko",
  "ts": "2026-07-03T19:08:41Z"
 },
 "TRADE@BSC": {
  "usd": 0.00053996,
  "source": "CoinGecko",
  "ts": "2026-07-03T19:08:41Z"
 },
 "TRIBE@Ethereum": {
  "usd": 0.290127,
  "source": "CoinGecko",
  "ts": "2026-07-03T19:08:41Z"
 },
 "TRU@Ethereum": {
  "usd": 0.00082763,
  "source": "CoinGecko",
  "ts": "2026-07-03T19:08:41Z"
 },
 "TRX@BSC": {
  "usd": 0.317208,
  "source": "CoinGecko",
  "ts": "2026-07-03T19:08:41Z"
 },
 "TSD@Avalanche": {
  "usd": 0.449106,
  "source": "CoinGecko",
  "ts": "2026-07-03T19:08:41Z"
 },
 "UBT@Ethereum": {
  "usd": 0.0268089,
  "source": "CoinGecko",
  "ts": "2026-07-03T19:08:41Z"
 },
 "UFO@Ethereum": {
  "usd": 3.0296e-08,
  "source": "CoinGecko",
  "ts": "2026-07-03T19:08:41Z"
 },
 "USDP@Ethereum": {
  "usd": 0.999622,
  "source": "CoinGecko",
  "ts": "2026-07-03T19:08:41Z"
 },
 "UST@Ethereum": {
  "usd": 0.00568196,
  "source": "CoinGecko",
  "ts": "2026-07-03T19:08:41Z"
 },
 "VISION@Polygon": {
  "usd": 0.107841,
  "source": "CoinGecko",
  "ts": "2026-07-03T19:08:41Z"
 },
 "VISR@Arbitrum": {
  "usd": 0.00010165,
  "source": "CoinGecko",
  "ts": "2026-07-03T19:08:41Z"
 },
 "WET@Avalanche": {
  "usd": 0.099307,
  "source": "CoinGecko",
  "ts": "2026-07-03T19:08:41Z"
 },
 "WEX@BSC": {
  "usd": 5.86e-06,
  "source": "CoinGecko",
  "ts": "2026-07-03T19:08:41Z"
 },
 "XFT@Ethereum": {
  "usd": 0.059704,
  "source": "CoinGecko",
  "ts": "2026-07-03T19:08:41Z"
 },
 "ZIL@BSC": {
  "usd": 0.00303045,
  "source": "CoinGecko",
  "ts": "2026-07-03T19:08:41Z"
 },
 "ZIL@Ethereum": {
  "usd": 0.00303045,
  "source": "CoinGecko",
  "ts": "2026-07-03T19:08:41Z"
 },
 "8PAY@BSC": {
  "usd": 0.00042951,
  "source": "CoinGecko",
  "ts": "2026-07-03T19:08:41Z"
 },
 "ABNBC@BSC": {
  "usd": 1.53,
  "source": "CoinGecko",
  "ts": "2026-07-03T19:08:41Z"
 },
 "AELIN@Optimism": {
  "usd": 359.27,
  "source": "CoinGecko",
  "ts": "2026-07-03T19:08:41Z"
 },
 "AETHC@Ethereum": {
  "usd": 2116.68,
  "source": "CoinGecko",
  "ts": "2026-07-03T19:08:41Z"
 },
 "AKRO@Ethereum": {
  "usd": 4.52e-06,
  "source": "CoinGecko",
  "ts": "2026-07-03T19:08:41Z"
 },
 "ALGB@Polygon": {
  "usd": 1.906e-05,
  "source": "CoinGecko",
  "ts": "2026-07-03T19:08:41Z"
 },
 "ALPA@BSC": {
  "usd": 0.01938246,
  "source": "CoinGecko",
  "ts": "2026-07-03T19:08:41Z"
 },
 "AMAAVE@Polygon": {
  "usd": 87.12,
  "source": "CoinGecko",
  "ts": "2026-07-03T19:08:41Z"
 },
 "ANRX@Polygon": {
  "usd": 5.306e-05,
  "source": "CoinGecko",
  "ts": "2026-07-03T19:08:41Z"
 },
 "ANT@Ethereum": {
  "usd": 0.04922745,
  "source": "CoinGecko",
  "ts": "2026-07-03T19:08:41Z"
 },
 "ARIA20@Polygon": {
  "usd": 0.01600278,
  "source": "CoinGecko",
  "ts": "2026-07-03T19:08:41Z"
 },
 "ARPA@BSC": {
  "usd": 0.01054891,
  "source": "CoinGecko",
  "ts": "2026-07-03T19:08:41Z"
 },
 "AST@Ethereum": {
  "usd": 0.00461125,
  "source": "CoinGecko",
  "ts": "2026-07-03T19:08:41Z"
 },
 "AUC@Ethereum": {
  "usd": 0.00037816,
  "source": "CoinGecko",
  "ts": "2026-07-03T19:08:41Z"
 },
 "AUCTION@Ethereum": {
  "usd": 3.38,
  "source": "CoinGecko",
  "ts": "2026-07-03T19:08:41Z"
 },
 "AUDIO@Ethereum": {
  "usd": 0.01355467,
  "source": "CoinGecko",
  "ts": "2026-07-03T19:08:41Z"
 },
 "AXIAL@Avalanche": {
  "usd": 4.86e-06,
  "source": "CoinGecko",
  "ts": "2026-07-03T19:08:41Z"
 },
 "AZUKI@Polygon": {
  "usd": 0.00036987,
  "source": "CoinGecko",
  "ts": "2026-07-03T19:08:41Z"
 },
 "BABYCAKE@BSC": {
  "usd": 5.49e-06,
  "source": "CoinGecko",
  "ts": "2026-07-03T19:08:41Z"
 },
 "BANK@Ethereum": {
  "usd": 0.00014567,
  "source": "CoinGecko",
  "ts": "2026-07-03T19:08:41Z"
 },
 "BAO@Ethereum": {
  "usd": 9.0322e-08,
  "source": "CoinGecko",
  "ts": "2026-07-03T19:08:41Z"
 },
 "BEL@BSC": {
  "usd": 0.094946,
  "source": "CoinGecko",
  "ts": "2026-07-03T19:08:41Z"
 },
 "BFI@BSC": {
  "usd": 0.058548,
  "source": "CoinGecko",
  "ts": "2026-07-03T19:08:41Z"
 },
 "BICO@Ethereum": {
  "usd": 0.01586629,
  "source": "CoinGecko",
  "ts": "2026-07-03T19:08:41Z"
 },
 "BIT@Ethereum": {
  "usd": 0.477614,
  "source": "CoinGecko",
  "ts": "2026-07-03T19:08:41Z"
 },
 "BLZ@Ethereum": {
  "usd": 0.00755968,
  "source": "CoinGecko",
  "ts": "2026-07-03T19:08:41Z"
 },
 "BMON@BSC": {
  "usd": 0.00141627,
  "source": "CoinGecko",
  "ts": "2026-07-03T19:08:41Z"
 },
 "BONDLY@BSC": {
  "usd": 0.00013978,
  "source": "CoinGecko",
  "ts": "2026-07-03T19:08:41Z"
 },
 "BORING@BSC": {
  "usd": 4.082e-05,
  "source": "CoinGecko",
  "ts": "2026-07-03T19:08:41Z"
 },
 "BPT@Avalanche": {
  "usd": 2.639e-05,
  "source": "CoinGecko",
  "ts": "2026-07-03T19:08:41Z"
 },
 "BSGG@Avalanche": {
  "usd": 0.0007367,
  "source": "CoinGecko",
  "ts": "2026-07-03T19:08:41Z"
 },
 "BTTOLD@BSC": {
  "usd": 0.00031589,
  "source": "CoinGecko",
  "ts": "2026-07-03T19:08:41Z"
 },
 "BUX@BSC": {
  "usd": 0.00178731,
  "source": "CoinGecko",
  "ts": "2026-07-03T19:08:41Z"
 },
 "BZRX@Ethereum": {
  "usd": 0.00076293,
  "source": "CoinGecko",
  "ts": "2026-07-03T19:08:41Z"
 },
 "CETH@Ethereum": {
  "usd": 34.95,
  "source": "CoinGecko",
  "ts": "2026-07-03T19:08:41Z"
 },
 "CLY@Avalanche": {
  "usd": 0.00032444,
  "source": "CoinGecko",
  "ts": "2026-07-03T19:08:41Z"
 },
 "COMBO@Ethereum": {
  "usd": 0.00025971,
  "source": "CoinGecko",
  "ts": "2026-07-03T19:08:41Z"
 },
 "CORE@Ethereum": {
  "usd": 4825.53,
  "source": "CoinGecko",
  "ts": "2026-07-03T19:08:41Z"
 },
 "COVAL@Ethereum": {
  "usd": 4.199e-05,
  "source": "CoinGecko",
  "ts": "2026-07-03T19:08:41Z"
 },
 "CQT@Ethereum": {
  "usd": 0.00079857,
  "source": "CoinGecko",
  "ts": "2026-07-03T19:08:41Z"
 },
 "CUSDC@Ethereum": {
  "usd": 0.02531937,
  "source": "CoinGecko",
  "ts": "2026-07-03T19:08:41Z"
 },
 "CVC@Ethereum": {
  "usd": 0.02127228,
  "source": "CoinGecko",
  "ts": "2026-07-03T19:08:41Z"
 },
 "CVP@Ethereum": {
  "usd": 0.00177127,
  "source": "CoinGecko",
  "ts": "2026-07-03T19:08:41Z"
 },
 "CYC@BSC": {
  "usd": 1.93,
  "source": "CoinGecko",
  "ts": "2026-07-03T19:08:41Z"
 },
 "CYCLE@Avalanche": {
  "usd": 0.01678249,
  "source": "CoinGecko",
  "ts": "2026-07-03T19:08:41Z"
 },
 "DDX@Ethereum": {
  "usd": 0.04972669,
  "source": "CoinGecko",
  "ts": "2026-07-03T19:08:41Z"
 },
 "DEGEN@Ethereum": {
  "usd": 3.24e-06,
  "source": "CoinGecko",
  "ts": "2026-07-03T19:08:41Z"
 },
 "DERC@Ethereum": {
  "usd": 0.00279697,
  "source": "CoinGecko",
  "ts": "2026-07-03T19:08:41Z"
 },
 "DEV@Ethereum": {
  "usd": 0.00106825,
  "source": "CoinGecko",
  "ts": "2026-07-03T19:08:41Z"
 },
 "DF@Ethereum": {
  "usd": 0.0003898,
  "source": "CoinGecko",
  "ts": "2026-07-03T19:08:41Z"
 },
 "DFX@Polygon": {
  "usd": 0.00056596,
  "source": "CoinGecko",
  "ts": "2026-07-03T19:08:41Z"
 },
 "DFYN@Polygon": {
  "usd": 0.00027085,
  "source": "CoinGecko",
  "ts": "2026-07-03T19:08:41Z"
 },
 "DG@Polygon": {
  "usd": 0.098338,
  "source": "CoinGecko",
  "ts": "2026-07-03T19:08:41Z"
 },
 "DHT@Ethereum": {
  "usd": 0.0263149,
  "source": "CoinGecko",
  "ts": "2026-07-03T19:08:41Z"
 },
 "DMT@Polygon": {
  "usd": 1.91,
  "source": "CoinGecko",
  "ts": "2026-07-03T19:08:41Z"
 },
 "DNT@Ethereum": {
  "usd": 0.00548783,
  "source": "CoinGecko",
  "ts": "2026-07-03T19:08:41Z"
 },
 "DSLA@Polygon": {
  "usd": 1.309e-05,
  "source": "CoinGecko",
  "ts": "2026-07-03T19:08:41Z"
 },
 "DUCK@Ethereum": {
  "usd": 3.302e-05,
  "source": "CoinGecko",
  "ts": "2026-07-03T19:08:41Z"
 },
 "DVF@Ethereum": {
  "usd": 0.544063,
  "source": "CoinGecko",
  "ts": "2026-07-03T19:08:41Z"
 },
 "ERSDL@Ethereum": {
  "usd": 4.64e-06,
  "source": "CoinGecko",
  "ts": "2026-07-03T19:08:41Z"
 },
 "ETH2X-FLI-P@Polygon": {
  "usd": 5.18,
  "source": "CoinGecko",
  "ts": "2026-07-03T19:08:41Z"
 },
 "EXRD@Ethereum": {
  "usd": 0.00083061,
  "source": "CoinGecko",
  "ts": "2026-07-03T19:08:41Z"
 },
 "FEED@Avalanche": {
  "usd": 9.3e-06,
  "source": "CoinGecko",
  "ts": "2026-07-03T19:08:41Z"
 },
 "FOR@BSC": {
  "usd": 6.297e-05,
  "source": "CoinGecko",
  "ts": "2026-07-03T19:08:41Z"
 },
 "FUN@Ethereum": {
  "usd": 0.00303678,
  "source": "CoinGecko",
  "ts": "2026-07-03T19:08:41Z"
 },
 "GAME@Polygon": {
  "usd": 0.00058735,
  "source": "CoinGecko",
  "ts": "2026-07-03T19:08:41Z"
 },
 "GDL@Avalanche": {
  "usd": 1.218e-05,
  "source": "CoinGecko",
  "ts": "2026-07-03T19:08:41Z"
 },
 "GFARM2@Polygon": {
  "usd": 1133.03,
  "source": "CoinGecko",
  "ts": "2026-07-03T19:08:41Z"
 },
 "GTC@Ethereum": {
  "usd": 0.075273,
  "source": "CoinGecko",
  "ts": "2026-07-03T19:08:41Z"
 },
 "GUM@BSC": {
  "usd": 0.0050075,
  "source": "CoinGecko",
  "ts": "2026-07-03T19:08:41Z"
 },
 "GYEN@Ethereum": {
  "usd": 0.00219065,
  "source": "CoinGecko",
  "ts": "2026-07-03T19:08:41Z"
 },
 "HAY@BSC": {
  "usd": 0.997738,
  "source": "CoinGecko",
  "ts": "2026-07-03T19:08:41Z"
 },
 "HEC@Avalanche": {
  "usd": 0.00031693,
  "source": "CoinGecko",
  "ts": "2026-07-03T19:08:41Z"
 },
 "HEZ@Ethereum": {
  "usd": 3.07,
  "source": "CoinGecko",
  "ts": "2026-07-03T19:08:41Z"
 },
 "HND@Arbitrum": {
  "usd": 0.00054026,
  "source": "CoinGecko",
  "ts": "2026-07-03T19:08:41Z"
 },
 "HON@Avalanche": {
  "usd": 0.001403,
  "source": "CoinGecko",
  "ts": "2026-07-03T19:08:41Z"
 },
 "HOT@Ethereum": {
  "usd": 0.00030492,
  "source": "CoinGecko",
  "ts": "2026-07-03T19:08:41Z"
 },
 "HT@Ethereum": {
  "usd": 0.080865,
  "source": "CoinGecko",
  "ts": "2026-07-03T19:08:41Z"
 },
 "HUSD@Ethereum": {
  "usd": 0.03693555,
  "source": "CoinGecko",
  "ts": "2026-07-03T19:08:41Z"
 },
 "ICE@Ethereum": {
  "usd": 0.01236318,
  "source": "CoinGecko",
  "ts": "2026-07-03T19:08:41Z"
 },
 "IF@BSC": {
  "usd": 0.0026689,
  "source": "CoinGecko",
  "ts": "2026-07-03T19:08:41Z"
 },
 "INSUR@BSC": {
  "usd": 0.00136378,
  "source": "CoinGecko",
  "ts": "2026-07-03T19:08:41Z"
 },
 "INV@Ethereum": {
  "usd": 10.79,
  "source": "CoinGecko",
  "ts": "2026-07-03T19:08:41Z"
 },
 "IRIS@Polygon": {
  "usd": 0.0010713,
  "source": "CoinGecko",
  "ts": "2026-07-03T19:08:41Z"
 },
 "IRON@Polygon": {
  "usd": 7.297e-05,
  "source": "CoinGecko",
  "ts": "2026-07-03T19:08:41Z"
 },
 "JPYC@Polygon": {
  "usd": 0.00774849,
  "source": "CoinGecko",
  "ts": "2026-07-03T19:08:41Z"
 },
 "JRT@Ethereum": {
  "usd": 0.00086368,
  "source": "CoinGecko",
  "ts": "2026-07-03T19:08:41Z"
 },
 "KISHU@Ethereum": {
  "usd": 1.22655e-10,
  "source": "CoinGecko",
  "ts": "2026-07-03T19:08:41Z"
 },
 "KLIMA@Polygon": {
  "usd": 0.00137042,
  "source": "CoinGecko",
  "ts": "2026-07-03T19:08:41Z"
 },
 "KNC@Polygon": {
  "usd": 0.11306,
  "source": "CoinGecko",
  "ts": "2026-07-03T19:08:41Z"
 },
 "KOM@Polygon": {
  "usd": 0.00016739,
  "source": "CoinGecko",
  "ts": "2026-07-03T19:08:41Z"
 },
 "LCX@Ethereum": {
  "usd": 0.0225528,
  "source": "CoinGecko",
  "ts": "2026-07-03T19:08:41Z"
 },
 "LEND@Ethereum": {
  "usd": 0.118405,
  "source": "CoinGecko",
  "ts": "2026-07-03T19:08:41Z"
 },
 "LIEN@BSC": {
  "usd": 0.146973,
  "source": "CoinGecko",
  "ts": "2026-07-03T19:08:41Z"
 },
 "LON@Ethereum": {
  "usd": 0.177875,
  "source": "CoinGecko",
  "ts": "2026-07-03T19:08:41Z"
 },
 "LOST@Avalanche": {
  "usd": 0.00017263,
  "source": "CoinGecko",
  "ts": "2026-07-03T19:08:41Z"
 },
 "LUNC@Ethereum": {
  "usd": 9.4e-06,
  "source": "CoinGecko",
  "ts": "2026-07-03T19:08:41Z"
 },
 "LYRA@Optimism": {
  "usd": 0.00012009,
  "source": "CoinGecko",
  "ts": "2026-07-03T19:08:41Z"
 },
 "MAHA@Ethereum": {
  "usd": 0.00613552,
  "source": "CoinGecko",
  "ts": "2026-07-03T19:08:41Z"
 },
 "MARSH@BSC": {
  "usd": 0.0002438,
  "source": "CoinGecko",
  "ts": "2026-07-03T19:08:41Z"
 },
 "MASQ@Ethereum": {
  "usd": 0.00935552,
  "source": "CoinGecko",
  "ts": "2026-07-03T19:08:41Z"
 },
 "MDT@Ethereum": {
  "usd": 0.00279768,
  "source": "CoinGecko",
  "ts": "2026-07-03T19:08:41Z"
 },
 "MIR@Ethereum": {
  "usd": 0.00307572,
  "source": "CoinGecko",
  "ts": "2026-07-03T19:08:41Z"
 },
 "MIST@Ethereum": {
  "usd": 0.169085,
  "source": "CoinGecko",
  "ts": "2026-07-03T19:08:41Z"
 },
 "MOD@Polygon": {
  "usd": 0.02256735,
  "source": "CoinGecko",
  "ts": "2026-07-03T19:08:41Z"
 },
 "MTL@Ethereum": {
  "usd": 0.232027,
  "source": "CoinGecko",
  "ts": "2026-07-03T19:08:41Z"
 },
 "MULTI@Ethereum": {
  "usd": 0.08712,
  "source": "CoinGecko",
  "ts": "2026-07-03T19:08:41Z"
 },
 "MYST@Polygon": {
  "usd": 0.089813,
  "source": "CoinGecko",
  "ts": "2026-07-03T19:08:41Z"
 },
 "NCT@Ethereum": {
  "usd": 0.00534467,
  "source": "CoinGecko",
  "ts": "2026-07-03T19:08:41Z"
 },
 "NDX@Ethereum": {
  "usd": 0.0011505,
  "source": "CoinGecko",
  "ts": "2026-07-03T19:08:41Z"
 },
 "NFTX@Ethereum": {
  "usd": 5.0,
  "source": "CoinGecko",
  "ts": "2026-07-03T19:08:41Z"
 },
 "NYAN@Arbitrum": {
  "usd": 0.00029384,
  "source": "CoinGecko",
  "ts": "2026-07-03T19:08:41Z"
 },
 "ODDZ@BSC": {
  "usd": 0.00017028,
  "source": "CoinGecko",
  "ts": "2026-07-03T19:08:41Z"
 },
 "OMEN@Polygon": {
  "usd": 0.00071043,
  "source": "CoinGecko",
  "ts": "2026-07-03T19:08:41Z"
 },
 "OOE@Avalanche": {
  "usd": 0.00032168,
  "source": "CoinGecko",
  "ts": "2026-07-03T19:08:41Z"
 },
 "OPIUM@Ethereum": {
  "usd": 0.01100533,
  "source": "CoinGecko",
  "ts": "2026-07-03T19:08:41Z"
 },
 "ORBS@BSC": {
  "usd": 0.00591232,
  "source": "CoinGecko",
  "ts": "2026-07-03T19:08:41Z"
 },
 "ORCA@Avalanche": {
  "usd": 5.469e-05,
  "source": "CoinGecko",
  "ts": "2026-07-03T19:08:41Z"
 },
 "OXT@Ethereum": {
  "usd": 0.00383223,
  "source": "CoinGecko",
  "ts": "2026-07-03T19:08:41Z"
 },
 "PBTC@BSC": {
  "usd": 122.98,
  "source": "CoinGecko",
  "ts": "2026-07-03T19:08:41Z"
 },
 "PECO@Polygon": {
  "usd": 2.64,
  "source": "CoinGecko",
  "ts": "2026-07-03T19:08:41Z"
 },
 "PICKLE@Ethereum": {
  "usd": 0.00957169,
  "source": "CoinGecko",
  "ts": "2026-07-03T19:08:41Z"
 },
 "PLU@Ethereum": {
  "usd": 0.119004,
  "source": "CoinGecko",
  "ts": "2026-07-03T19:08:41Z"
 },
 "POLAR@Avalanche": {
  "usd": 5.08e-06,
  "source": "CoinGecko",
  "ts": "2026-07-03T19:08:41Z"
 },
 "POLS@Ethereum": {
  "usd": 0.060572,
  "source": "CoinGecko",
  "ts": "2026-07-03T19:08:41Z"
 },
 "POLYBUNNY@Polygon": {
  "usd": 0.00246175,
  "source": "CoinGecko",
  "ts": "2026-07-03T19:08:41Z"
 },
 "POND@Ethereum": {
  "usd": 0.00117336,
  "source": "CoinGecko",
  "ts": "2026-07-03T19:08:41Z"
 },
 "PPDEX@Polygon": {
  "usd": 0.00963811,
  "source": "CoinGecko",
  "ts": "2026-07-03T19:08:41Z"
 },
 "PRE@Ethereum": {
  "usd": 0.00065627,
  "source": "CoinGecko",
  "ts": "2026-07-03T19:08:41Z"
 },
 "PROM@BSC": {
  "usd": 1.13,
  "source": "CoinGecko",
  "ts": "2026-07-03T19:08:41Z"
 },
 "PRQ@Ethereum": {
  "usd": 0.0003401,
  "source": "CoinGecko",
  "ts": "2026-07-03T19:08:41Z"
 },
 "PSP@Ethereum": {
  "usd": 0.00103721,
  "source": "CoinGecko",
  "ts": "2026-07-03T19:08:41Z"
 },
 "QRDO@Ethereum": {
  "usd": 9.548e-05,
  "source": "CoinGecko",
  "ts": "2026-07-03T19:08:41Z"
 },
 "RACEX@Avalanche": {
  "usd": 1.565e-05,
  "source": "CoinGecko",
  "ts": "2026-07-03T19:08:41Z"
 },
 "RAD@Ethereum": {
  "usd": 0.216361,
  "source": "CoinGecko",
  "ts": "2026-07-03T19:08:41Z"
 },
 "RBC@Ethereum": {
  "usd": 0.00359798,
  "source": "CoinGecko",
  "ts": "2026-07-03T19:08:41Z"
 },
 "RCN@Ethereum": {
  "usd": 0.00050823,
  "source": "CoinGecko",
  "ts": "2026-07-03T19:08:41Z"
 },
 "RENBCH@Ethereum": {
  "usd": 1354.5,
  "source": "CoinGecko",
  "ts": "2026-07-03T19:08:41Z"
 },
 "RENZEC@Ethereum": {
  "usd": 40.86,
  "source": "CoinGecko",
  "ts": "2026-07-03T19:08:41Z"
 },
 "RFG@BSC": {
  "usd": 4.447e-11,
  "source": "CoinGecko",
  "ts": "2026-07-03T19:08:41Z"
 },
 "RFOX@BSC": {
  "usd": 0.00011097,
  "source": "CoinGecko",
  "ts": "2026-07-03T19:08:41Z"
 },
 "RLY@Ethereum": {
  "usd": 3.291e-05,
  "source": "CoinGecko",
  "ts": "2026-07-03T19:08:41Z"
 },
 "RUNE@Ethereum": {
  "usd": 0.00999093,
  "source": "CoinGecko",
  "ts": "2026-07-03T19:08:41Z"
 },
 "SAFLE@Polygon": {
  "usd": 4.04e-06,
  "source": "CoinGecko",
  "ts": "2026-07-03T19:08:41Z"
 },
 "SBDO@BSC": {
  "usd": 0.968695,
  "source": "CoinGecko",
  "ts": "2026-07-03T19:08:41Z"
 },
 "SETH@Optimism": {
  "usd": 333.33,
  "source": "CoinGecko",
  "ts": "2026-07-03T19:08:41Z"
 },
 "SETH2@Ethereum": {
  "usd": 1604.76,
  "source": "CoinGecko",
  "ts": "2026-07-03T19:08:41Z"
 },
 "SFI@Ethereum": {
  "usd": 101.96,
  "source": "CoinGecko",
  "ts": "2026-07-03T19:08:41Z"
 },
 "SI@Ethereum": {
  "usd": 0.00313156,
  "source": "CoinGecko",
  "ts": "2026-07-03T19:08:41Z"
 },
 "SKILL@BSC": {
  "usd": 0.06909,
  "source": "CoinGecko",
  "ts": "2026-07-03T19:08:41Z"
 },
 "SKL@Ethereum": {
  "usd": 0.00358867,
  "source": "CoinGecko",
  "ts": "2026-07-03T19:08:41Z"
 },
 "SMRTR@Avalanche": {
  "usd": 1.3037e-08,
  "source": "CoinGecko",
  "ts": "2026-07-03T19:08:41Z"
 },
 "SNT@Ethereum": {
  "usd": 0.00731892,
  "source": "CoinGecko",
  "ts": "2026-07-03T19:08:41Z"
 },
 "SPANK@Ethereum": {
  "usd": 0.00426744,
  "source": "CoinGecko",
  "ts": "2026-07-03T19:08:41Z"
 },
 "SPS@BSC": {
  "usd": 0.0029476,
  "source": "CoinGecko",
  "ts": "2026-07-03T19:08:41Z"
 },
 "STAKE@Ethereum": {
  "usd": 0.03356738,
  "source": "CoinGecko",
  "ts": "2026-07-03T19:08:41Z"
 },
 "STAX@BSC": {
  "usd": 0.06714,
  "source": "CoinGecko",
  "ts": "2026-07-03T19:08:41Z"
 },
 "STMATIC@Polygon": {
  "usd": 0.083997,
  "source": "CoinGecko",
  "ts": "2026-07-03T19:08:41Z"
 },
 "STRONG@Ethereum": {
  "usd": 0.509444,
  "source": "CoinGecko",
  "ts": "2026-07-03T19:08:41Z"
 },
 "STRP@Arbitrum": {
  "usd": 0.0078394,
  "source": "CoinGecko",
  "ts": "2026-07-03T19:08:41Z"
 },
 "SUKU@Ethereum": {
  "usd": 0.00472318,
  "source": "CoinGecko",
  "ts": "2026-07-03T19:08:41Z"
 },
 "SWAP@Ethereum": {
  "usd": 0.04424972,
  "source": "CoinGecko",
  "ts": "2026-07-03T19:08:41Z"
 },
 "SWINGBY@BSC": {
  "usd": 2.146e-05,
  "source": "CoinGecko",
  "ts": "2026-07-03T19:08:41Z"
 },
 "TCR@Arbitrum": {
  "usd": 0.00017289,
  "source": "CoinGecko",
  "ts": "2026-07-03T19:08:41Z"
 },
 "THG@BSC": {
  "usd": 0.00010669,
  "source": "CoinGecko",
  "ts": "2026-07-03T19:08:41Z"
 },
 "TIME@Ethereum": {
  "usd": 0.276366,
  "source": "CoinGecko",
  "ts": "2026-07-03T19:08:41Z"
 },
 "TUNDRA@Avalanche": {
  "usd": 0.05076,
  "source": "CoinGecko",
  "ts": "2026-07-03T19:08:41Z"
 },
 "TVK@Ethereum": {
  "usd": 0.00021218,
  "source": "CoinGecko",
  "ts": "2026-07-03T19:08:41Z"
 },
 "TXL@BSC": {
  "usd": 0.00078788,
  "source": "CoinGecko",
  "ts": "2026-07-03T19:08:41Z"
 },
 "UBXT@BSC": {
  "usd": 0.00012024,
  "source": "CoinGecko",
  "ts": "2026-07-03T19:08:41Z"
 },
 "VTX@Avalanche": {
  "usd": 0.00086265,
  "source": "CoinGecko",
  "ts": "2026-07-03T19:08:41Z"
 },
 "WATCH@BSC": {
  "usd": 0.00592136,
  "source": "CoinGecko",
  "ts": "2026-07-03T19:08:41Z"
 },
 "WMEMO@Avalanche": {
  "usd": 275.01,
  "source": "CoinGecko",
  "ts": "2026-07-03T19:08:41Z"
 },
 "WNXM@Ethereum": {
  "usd": 46.69,
  "source": "CoinGecko",
  "ts": "2026-07-03T19:08:41Z"
 },
 "WOM@BSC": {
  "usd": 0.00069838,
  "source": "CoinGecko",
  "ts": "2026-07-03T19:08:41Z"
 },
 "WONE@BSC": {
  "usd": 0.00130861,
  "source": "CoinGecko",
  "ts": "2026-07-03T19:08:41Z"
 },
 "WOOP@BSC": {
  "usd": 0.00149829,
  "source": "CoinGecko",
  "ts": "2026-07-03T19:08:41Z"
 },
 "WRX@Polygon": {
  "usd": 0.02029941,
  "source": "CoinGecko",
  "ts": "2026-07-03T19:08:41Z"
 },
 "X2Y2@Ethereum": {
  "usd": 0.00076918,
  "source": "CoinGecko",
  "ts": "2026-07-03T19:08:41Z"
 },
 "XCHF@Ethereum": {
  "usd": 0.566534,
  "source": "CoinGecko",
  "ts": "2026-07-03T19:08:41Z"
 },
 "XDEFI@Ethereum": {
  "usd": 0.00100913,
  "source": "CoinGecko",
  "ts": "2026-07-03T19:08:41Z"
 },
 "XED@BSC": {
  "usd": 0.00089238,
  "source": "CoinGecko",
  "ts": "2026-07-03T19:08:41Z"
 },
 "XEND@BSC": {
  "usd": 0.00167751,
  "source": "CoinGecko",
  "ts": "2026-07-03T19:08:41Z"
 },
 "XGEM@Polygon": {
  "usd": 1.555e-05,
  "source": "CoinGecko",
  "ts": "2026-07-03T19:08:41Z"
 },
 "XMARK@BSC": {
  "usd": 0.00560636,
  "source": "CoinGecko",
  "ts": "2026-07-03T19:08:41Z"
 },
 "XPR@Ethereum": {
  "usd": 0.00214464,
  "source": "CoinGecko",
  "ts": "2026-07-03T19:08:41Z"
 },
 "XSUSHI@Ethereum": {
  "usd": 0.255349,
  "source": "CoinGecko",
  "ts": "2026-07-03T19:08:41Z"
 },
 "YAY@Avalanche": {
  "usd": 0.00012413,
  "source": "CoinGecko",
  "ts": "2026-07-03T19:08:41Z"
 },
 "YFII@Ethereum": {
  "usd": 25.72,
  "source": "CoinGecko",
  "ts": "2026-07-03T19:08:41Z"
 },
 "YTS@Avalanche": {
  "usd": 0.00079826,
  "source": "CoinGecko",
  "ts": "2026-07-03T19:08:41Z"
 },
 "YUSD@Avalanche": {
  "usd": 0.99612,
  "source": "CoinGecko",
  "ts": "2026-07-03T19:08:41Z"
 },
 "ZOO@Avalanche": {
  "usd": 9.566e-05,
  "source": "CoinGecko",
  "ts": "2026-07-03T19:08:41Z"
 },
 "aAVAXb@Avalanche": {
  "usd": 30.26,
  "source": "CoinGecko",
  "ts": "2026-07-03T19:08:41Z"
 },
 "0XMR@Ethereum": {
  "usd": 0.01510117,
  "source": "CoinGecko",
  "ts": "2026-07-03T19:08:41Z"
 },
 "2KEY@Ethereum": {
  "usd": 0.00028997,
  "source": "CoinGecko",
  "ts": "2026-07-03T19:08:41Z"
 },
 "ABAT@Ethereum": {
  "usd": 0.083141,
  "source": "CoinGecko",
  "ts": "2026-07-03T19:08:41Z"
 },
 "ABI@Polygon": {
  "usd": 2.32,
  "source": "CoinGecko",
  "ts": "2026-07-03T19:08:41Z"
 },
 "ABLOCK@Avalanche": {
  "usd": 0.12352,
  "source": "CoinGecko",
  "ts": "2026-07-03T19:08:41Z"
 },
 "ABYSS@Ethereum": {
  "usd": 0.00269863,
  "source": "CoinGecko",
  "ts": "2026-07-03T19:08:41Z"
 },
 "ACAR@Polygon": {
  "usd": 1.83,
  "source": "CoinGecko",
  "ts": "2026-07-03T19:08:41Z"
 },
 "ACRE@Avalanche": {
  "usd": 2.123e-05,
  "source": "CoinGecko",
  "ts": "2026-07-03T19:08:41Z"
 },
 "ACS@BSC": {
  "usd": 0.125464,
  "source": "CoinGecko",
  "ts": "2026-07-03T19:08:41Z"
 },
 "ACSI@BSC": {
  "usd": 0.11922,
  "source": "CoinGecko",
  "ts": "2026-07-03T19:08:41Z"
 },
 "ADAI@Ethereum": {
  "usd": 0.999823,
  "source": "CoinGecko",
  "ts": "2026-07-03T19:08:41Z"
 },
 "ADAI@Avalanche": {
  "usd": 0.999823,
  "source": "CoinGecko",
  "ts": "2026-07-03T19:08:41Z"
 },
 "ADOGE@Arbitrum": {
  "usd": 1.7197e-08,
  "source": "CoinGecko",
  "ts": "2026-07-03T19:08:41Z"
 },
 "ADS@BSC": {
  "usd": 0.395243,
  "source": "CoinGecko",
  "ts": "2026-07-03T19:08:41Z"
 },
 "AERGO@Ethereum": {
  "usd": 0.02511342,
  "source": "CoinGecko",
  "ts": "2026-07-03T19:08:41Z"
 },
 "AGAC@Polygon": {
  "usd": 0.00182511,
  "source": "CoinGecko",
  "ts": "2026-07-03T19:08:41Z"
 },
 "AGF@Avalanche": {
  "usd": 6.308e-05,
  "source": "CoinGecko",
  "ts": "2026-07-03T19:08:41Z"
 },
 "AGLD@Ethereum": {
  "usd": 0.158716,
  "source": "CoinGecko",
  "ts": "2026-07-03T19:08:41Z"
 },
 "AKITAX@Avalanche": {
  "usd": 7.07157e-07,
  "source": "CoinGecko",
  "ts": "2026-07-03T19:08:41Z"
 },
 "AKNC@Ethereum": {
  "usd": 0.111941,
  "source": "CoinGecko",
  "ts": "2026-07-03T19:08:41Z"
 },
 "ALBT@Avalanche": {
  "usd": 4.505e-05,
  "source": "CoinGecko",
  "ts": "2026-07-03T19:08:41Z"
 },
 "ALINK@Avalanche": {
  "usd": 7.84,
  "source": "CoinGecko",
  "ts": "2026-07-03T19:08:41Z"
 },
 "ALINK@Ethereum": {
  "usd": 7.84,
  "source": "CoinGecko",
  "ts": "2026-07-03T19:08:41Z"
 },
 "ALU@BSC": {
  "usd": 0.00342796,
  "source": "CoinGecko",
  "ts": "2026-07-03T19:08:41Z"
 },
 "ALUSD@Ethereum": {
  "usd": 0.957272,
  "source": "CoinGecko",
  "ts": "2026-07-03T19:08:41Z"
 },
 "AMANA@Ethereum": {
  "usd": 0.07269,
  "source": "CoinGecko",
  "ts": "2026-07-03T19:08:41Z"
 },
 "AMATICC@Polygon": {
  "usd": 0.109417,
  "source": "CoinGecko",
  "ts": "2026-07-03T19:08:41Z"
 },
 "AMDAI@Polygon": {
  "usd": 0.999704,
  "source": "CoinGecko",
  "ts": "2026-07-03T19:08:41Z"
 },
 "AMKR@Ethereum": {
  "usd": 1370.45,
  "source": "CoinGecko",
  "ts": "2026-07-03T19:08:41Z"
 },
 "AMUSDC@Polygon": {
  "usd": 0.999617,
  "source": "CoinGecko",
  "ts": "2026-07-03T19:08:41Z"
 },
 "AMUSDT@Polygon": {
  "usd": 0.998875,
  "source": "CoinGecko",
  "ts": "2026-07-03T19:08:41Z"
 },
 "AMWBTC@Polygon": {
  "usd": 62049.0,
  "source": "CoinGecko",
  "ts": "2026-07-03T19:08:41Z"
 },
 "AMWETH@Polygon": {
  "usd": 1738.41,
  "source": "CoinGecko",
  "ts": "2026-07-03T19:08:41Z"
 },
 "AMWMATIC@Polygon": {
  "usd": 0.07333,
  "source": "CoinGecko",
  "ts": "2026-07-03T19:08:41Z"
 },
 "ANN@BSC": {
  "usd": 0.00350338,
  "source": "CoinGecko",
  "ts": "2026-07-03T19:08:41Z"
 },
 "AOG@BSC": {
  "usd": 0.00228338,
  "source": "CoinGecko",
  "ts": "2026-07-03T19:08:41Z"
 },
 "APEIN@Avalanche": {
  "usd": 0.0498848,
  "source": "CoinGecko",
  "ts": "2026-07-03T19:08:41Z"
 },
 "APW@Ethereum": {
  "usd": 0.01678687,
  "source": "CoinGecko",
  "ts": "2026-07-03T19:08:41Z"
 },
 "APX@BSC": {
  "usd": 0.221001,
  "source": "CoinGecko",
  "ts": "2026-07-03T19:08:41Z"
 },
 "ARBIS@Arbitrum": {
  "usd": 9.66449e-07,
  "source": "CoinGecko",
  "ts": "2026-07-03T19:08:41Z"
 },
 "ARBYS@Arbitrum": {
  "usd": 0.100932,
  "source": "CoinGecko",
  "ts": "2026-07-03T19:08:41Z"
 },
 "ARCH@Ethereum": {
  "usd": 0.01604733,
  "source": "CoinGecko",
  "ts": "2026-07-03T19:08:41Z"
 },
 "ARCX@Ethereum": {
  "usd": 0.00983217,
  "source": "CoinGecko",
  "ts": "2026-07-03T19:08:41Z"
 },
 "ARMOR@Ethereum": {
  "usd": 0.00017304,
  "source": "CoinGecko",
  "ts": "2026-07-03T19:08:41Z"
 },
 "ARNXM@Ethereum": {
  "usd": 44.28,
  "source": "CoinGecko",
  "ts": "2026-07-03T19:08:41Z"
 },
 "ASKO@Ethereum": {
  "usd": 2.1957e-07,
  "source": "CoinGecko",
  "ts": "2026-07-03T19:08:41Z"
 },
 "ASNX@Ethereum": {
  "usd": 0.232711,
  "source": "CoinGecko",
  "ts": "2026-07-03T19:08:41Z"
 },
 "ASUSD@Ethereum": {
  "usd": 0.269474,
  "source": "CoinGecko",
  "ts": "2026-07-03T19:08:41Z"
 },
 "ATA@BSC": {
  "usd": 0.00077136,
  "source": "CoinGecko",
  "ts": "2026-07-03T19:08:41Z"
 },
 "ATIS@Ethereum": {
  "usd": 0.0026242,
  "source": "CoinGecko",
  "ts": "2026-07-03T19:08:41Z"
 },
 "ATUSD@Ethereum": {
  "usd": 0.997948,
  "source": "CoinGecko",
  "ts": "2026-07-03T19:08:41Z"
 },
 "AURUM@Polygon": {
  "usd": 7.361e-05,
  "source": "CoinGecko",
  "ts": "2026-07-03T19:08:41Z"
 },
 "AUSDC@Avalanche": {
  "usd": 0.999817,
  "source": "CoinGecko",
  "ts": "2026-07-03T19:08:41Z"
 },
 "AUSDC@Ethereum": {
  "usd": 0.999466,
  "source": "CoinGecko",
  "ts": "2026-07-03T19:08:41Z"
 },
 "AUSDT@Ethereum": {
  "usd": 0.999099,
  "source": "CoinGecko",
  "ts": "2026-07-03T19:08:41Z"
 },
 "AUSDT@Avalanche": {
  "usd": 0.998748,
  "source": "CoinGecko",
  "ts": "2026-07-03T19:08:41Z"
 },
 "AWBTC@Ethereum": {
  "usd": 61714.0,
  "source": "CoinGecko",
  "ts": "2026-07-03T19:08:41Z"
 },
 "AWBTC@Avalanche": {
  "usd": 61714.0,
  "source": "CoinGecko",
  "ts": "2026-07-03T19:08:41Z"
 },
 "AWETH@Avalanche": {
  "usd": 1737.8,
  "source": "CoinGecko",
  "ts": "2026-07-03T19:08:41Z"
 },
 "AZRX@Ethereum": {
  "usd": 0.084035,
  "source": "CoinGecko",
  "ts": "2026-07-03T19:08:41Z"
 },
 "BASE@Ethereum": {
  "usd": 0.234927,
  "source": "CoinGecko",
  "ts": "2026-07-03T19:08:41Z"
 },
 "BASK@Ethereum": {
  "usd": 0.361464,
  "source": "CoinGecko",
  "ts": "2026-07-03T19:08:41Z"
 },
 "BBTC@Ethereum": {
  "usd": 61880.0,
  "source": "CoinGecko",
  "ts": "2026-07-03T19:08:41Z"
 },
 "BCDT@Ethereum": {
  "usd": 0.00849454,
  "source": "CoinGecko",
  "ts": "2026-07-03T19:08:41Z"
 },
 "BCMC@Polygon": {
  "usd": 0.00035265,
  "source": "CoinGecko",
  "ts": "2026-07-03T19:08:41Z"
 },
 "BCOIN@BSC": {
  "usd": 0.01518004,
  "source": "CoinGecko",
  "ts": "2026-07-03T19:08:41Z"
 },
 "BCT@Polygon": {
  "usd": 0.00066259,
  "source": "CoinGecko",
  "ts": "2026-07-03T19:08:41Z"
 },
 "BEPRO@Ethereum": {
  "usd": 0.00015686,
  "source": "CoinGecko",
  "ts": "2026-07-03T19:08:41Z"
 },
 "BETA@BSC": {
  "usd": 0.00661938,
  "source": "CoinGecko",
  "ts": "2026-07-03T19:08:41Z"
 },
 "SUI@Ethereum": {
  "usd": 0.761396,
  "source": "CoinGecko",
  "ts": "2026-07-03T19:08:41Z"
 },
 "NEAR@Ethereum": {
  "usd": 2.0,
  "source": "CoinGecko",
  "ts": "2026-07-03T19:08:41Z"
 },
 "TAO@Ethereum": {
  "usd": 214.68,
  "source": "CoinGecko",
  "ts": "2026-07-03T19:08:41Z"
 },
 "APT@Ethereum": {
  "usd": 0.618389,
  "source": "CoinGecko",
  "ts": "2026-07-03T19:08:41Z"
 },
 "THETA@Ethereum": {
  "usd": 0.140572,
  "source": "CoinGecko",
  "ts": "2026-07-03T19:08:41Z"
 },
 "ALGO@Ethereum": {
  "usd": 0.089019,
  "source": "CoinGecko",
  "ts": "2026-07-03T19:08:41Z"
 },
 "ICP@Ethereum": {
  "usd": 2.23,
  "source": "CoinGecko",
  "ts": "2026-07-03T19:08:41Z"
 },
 "VET@Ethereum": {
  "usd": 0.00468307,
  "source": "CoinGecko",
  "ts": "2026-07-03T19:08:41Z"
 },
 "ZEN@Ethereum": {
  "usd": 4.31,
  "source": "CoinGecko",
  "ts": "2026-07-03T19:08:41Z"
 },
 "XTZ@Ethereum": {
  "usd": 0.238755,
  "source": "CoinGecko",
  "ts": "2026-07-03T19:08:41Z"
 },
 "MINA@Ethereum": {
  "usd": 0.04522102,
  "source": "CoinGecko",
  "ts": "2026-07-03T19:08:41Z"
 },
 "FLOW@Ethereum": {
  "usd": 0.02810116,
  "source": "CoinGecko",
  "ts": "2026-07-03T19:08:41Z"
 },
 "KAVA@Ethereum": {
  "usd": 0.04544796,
  "source": "CoinGecko",
  "ts": "2026-07-03T19:08:41Z"
 },
 "ONE@Ethereum": {
  "usd": 0.00129775,
  "source": "CoinGecko",
  "ts": "2026-07-03T19:08:41Z"
 },
 "HBAR@Ethereum": {
  "usd": 0.072557,
  "source": "CoinGecko",
  "ts": "2026-07-03T19:08:41Z"
 },
 "XDC@Ethereum": {
  "usd": 0.02844522,
  "source": "CoinGecko",
  "ts": "2026-07-03T19:08:41Z"
 },
 "DASH@Ethereum": {
  "usd": 35.81,
  "source": "CoinGecko",
  "ts": "2026-07-03T19:08:41Z"
 },
 "BTT@BSC": {
  "usd": 2.64783e-07,
  "source": "CoinGecko",
  "ts": "2026-07-03T19:08:41Z"
 },
 "WIN@BSC": {
  "usd": 2.104e-05,
  "source": "CoinGecko",
  "ts": "2026-07-03T19:08:41Z"
 },
 "CKB@Ethereum": {
  "usd": 0.00094757,
  "source": "CoinGecko",
  "ts": "2026-07-03T19:08:41Z"
 },
 "STEEM@Ethereum": {
  "usd": 0.04161471,
  "source": "CoinGecko",
  "ts": "2026-07-03T19:08:41Z"
 },
 "KSM@Ethereum": {
  "usd": 3.26,
  "source": "CoinGecko",
  "ts": "2026-07-03T19:08:41Z"
 },
 "ICX@Ethereum": {
  "usd": 0.02539756,
  "source": "CoinGecko",
  "ts": "2026-07-03T19:08:41Z"
 },
 "KEKEC@Ethereum": {
  "usd": 2.43e-05,
  "source": "CoinGecko",
  "ts": "2026-07-03T19:08:41Z"
 },
 "MATIC@Ethereum": {
  "usd": 0.07311,
  "source": "DexScreener",
  "ts": "2026-07-03T19:08:41Z"
 },
 "POL@Ethereum": {
  "usd": 0.07359,
  "source": "DexScreener",
  "ts": "2026-07-03T19:08:41Z"
 },
 "GALXE@BSC": {
  "usd": 0.2662,
  "source": "DexScreener",
  "ts": "2026-07-03T19:08:41Z"
 },
 "IO@Solana": {
  "usd": 0.1766,
  "source": "DexScreener",
  "ts": "2026-07-03T19:08:41Z"
 },
 "BOLD@Ethereum": {
  "usd": 1.00016,
  "source": "DexScreener",
  "ts": "2026-07-03T19:08:41Z"
 },
 "GEARBOX@Ethereum": {
  "usd": 0.0004484,
  "source": "DexScreener",
  "ts": "2026-07-03T19:08:41Z"
 },
 "USD0@Ethereum": {
  "usd": 0.9989,
  "source": "DexScreener",
  "ts": "2026-07-03T19:08:41Z"
 },
 "AIXBT@Base": {
  "usd": 0.01995,
  "source": "DexScreener",
  "ts": "2026-07-03T19:08:41Z"
 },
 "SWEAT@Ethereum": {
  "usd": 0.0005257,
  "source": "DexScreener",
  "ts": "2026-07-03T19:08:41Z"
 },
 "ATM@BSC": {
  "usd": 0.07044,
  "source": "DexScreener",
  "ts": "2026-07-03T19:08:41Z"
 },
 "TYBG@Base": {
  "usd": 6.97e-06,
  "source": "DexScreener",
  "ts": "2026-07-03T19:08:41Z"
 },
 "BUILD@Base": {
  "usd": 2.035e-07,
  "source": "DexScreener",
  "ts": "2026-07-03T19:08:41Z"
 },
 "INDEX@Ethereum": {
  "usd": 0.2393,
  "source": "DexScreener",
  "ts": "2026-07-03T19:08:41Z"
 },
 "LISUSD@BSC": {
  "usd": 0.9984,
  "source": "DexScreener",
  "ts": "2026-07-03T19:08:41Z"
 },
 "PROM@Ethereum": {
  "usd": 1.13,
  "source": "DexScreener",
  "ts": "2026-07-03T19:08:41Z"
 },
 "TREMP@Solana": {
  "usd": 0.004491,
  "source": "DexScreener",
  "ts": "2026-07-03T19:08:41Z"
 },
 "GNON@Solana": {
  "usd": 0.0001247,
  "source": "DexScreener",
  "ts": "2026-07-03T19:08:41Z"
 },
 "SIGMA@Solana": {
  "usd": 0.001643,
  "source": "DexScreener",
  "ts": "2026-07-03T19:08:41Z"
 },
 "PRISMA@Ethereum": {
  "usd": 0.00803,
  "source": "DexScreener",
  "ts": "2026-07-03T19:08:41Z"
 },
 "MATIC_ETH@Ethereum": {
  "usd": 0.07311,
  "source": "DexScreener",
  "ts": "2026-07-03T19:08:41Z"
 },
 "SIREN@BSC": {
  "usd": 0.03379,
  "source": "DexScreener",
  "ts": "2026-07-03T19:08:41Z"
 },
 "WLFI@Ethereum": {
  "usd": 0.01863,
  "source": "DexScreener",
  "ts": "2026-07-03T19:08:41Z"
 },
 "XOR@Ethereum": {
  "usd": 5.732e-36,
  "source": "DexScreener",
  "ts": "2026-07-03T19:08:41Z"
 },
 "TRUTH@Solana": {
  "usd": 2.23e-05,
  "source": "DexScreener_search",
  "ts": "2026-07-03T19:08:41Z"
 },
 "SYRUP@Ethereum": {
  "usd": 0.2107,
  "source": "DexScreener_search",
  "ts": "2026-07-03T19:08:41Z"
 },
 "STACK@BSC": {
  "usd": 0.0001784,
  "source": "DexScreener_search",
  "ts": "2026-07-03T19:08:41Z"
 },
 "TigerOG@Base": {
  "usd": 8.584e-19,
  "source": "DexScreener",
  "ts": "2026-07-03T19:08:41Z"
 },
 "LionOG@Base": {
  "usd": 1.083e-19,
  "source": "DexScreener",
  "ts": "2026-07-03T19:08:41Z"
 },
 "FrogOG@Base": {
  "usd": 8.236e-20,
  "source": "DexScreener",
  "ts": "2026-07-03T19:08:41Z"
 },
 "WKC@Ethereum": {
  "usd": null,
  "source": "none",
  "ts": "2026-07-03T19:08:41Z",
  "error": "no price on DexScreener or GeckoTerminal \u2014 low/no liquidity"
 },
 "sUSD@Ethereum": {
  "usd": null,
  "source": "none",
  "ts": "2026-07-03T19:08:41Z",
  "error": "no price source resolved"
 }
}